{"input":"#Software: SGOS 192.168.1.1\r\n#Version: 1.0\r\n#Start-Date: 2018-01-31 01:01:20\r\n#Date: 2017-08-16 07:41:53\r\n#Fields: date time time-taken c-ip cs-username cs-auth-group s-supplier-name s-supplier-ip s-supplier-country s-supplier-failures x-exception-id sc-filter-result cs-categories cs(Referer) sc-status s-action cs-method rs(Content-Type) cs-uri-scheme cs-host cs-uri-port cs-uri-extension cs(User-Agent) s-ip sc-bytes cs-bytes x-virus-id x-bluecoat-application-name x-bluecoat-application-operation x-rs-certificate-observed-errors x-cs-ocsp-error x-rs-ocsp-error x-rs-connection-negotiated-cipher-strength x-rs-certificate-hostname x-rs-certificate-hostname-category cs-threat-risk x-rs-certificate-hostname-threat-risk c-connect-type x-bluecoat-reference-id cs-ip x-cs-connection-negotiated-cipher-strength x-cs-connection-negotiated-ssl-version cs(Accept-Language)\r\n#Remark: 1315300034 \"bc-wcf-b1-site-1\" \"192.168.1.1\" \"CND-SSL-tenant\"\r\n2018-02-02 18:31:16 1 192.168.1.1 - - play.google.com 192.168.1.1 None - tenant.content_filter_denied DENIED \"Shopping;Software Downloads\" - 0 DENIED unknown - ssl play.google.com 443 - - 192.168.1.1 0 0 - \"none\" \"none\" none - - high *.google.com \"Search Engines/Portals\" unavailable unavailable Transparent \"WA-LS-D_Standard-Deny2\" 192.168.1.1 high TLSv1.2 -\r\n2018-02-02 18:31:16 1 192.168.1.1 - - play.google.com 192.168.1.1 None - tenant.content_filter_denied DENIED \"Shopping;Software Downloads\" - 0 DENIED unknown - ssl play.google.com 443 - - 192.168.1.1 0 0 - \"none\" \"none\" none - - high *.google.com \"Search Engines/Portals\" unavailable unavailable Transparent \"WA-LS-D_Standard-Deny2\" 192.168.1.1 high TLSv1.2 -\r\n2018-02-02 18:31:16 1 192.168.1.1 - - play.google.com 192.168.1.1 None - tenant.content_filter_denied DENIED \"Shopping;Software Downloads\" - 0 DENIED unknown - ssl play.google.com 443 - - 192.168.1.1 0 0 - \"none\" \"none\" none - - high *.google.com \"Search Engines/Portals\" unavailable unavailable Transparent \"WA-LS-D_Standard-Deny2\" 192.168.1.1 high TLSv1.2 -\r\n2018-02-02 18:31:16 1 192.168.1.1 - - play.google.com 192.168.1.1 None - tenant.content_filter_denied DENIED \"Shopping;Software Downloads\" - 0 DENIED unknown - ssl play.google.com 443 - - 192.168.1.1 0 0 - \"none\" \"none\" none - - high *.google.com \"Search Engines/Portals\" unavailable unavailable Transparent \"WA-LS-D_Standard-Deny2\" 192.168.1.1 high TLSv1.2 -\r\n2018-02-02 18:31:16 1 192.168.1.1 - - play.google.com 192.168.1.1 None - tenant.content_filter_denied DENIED \"Shopping;Software Downloads\" - 0 DENIED unknown - ssl play.google.com 443 - - 192.168.1.1 0 0 - \"none\" \"none\" none - - high *.google.com \"Search Engines/Portals\" unavailable unavailable Transparent \"WA-LS-D_Standard-Deny2\" 192.168.1.1 high TLSv1.2 -\r\n2018-02-02 18:31:16 1 192.168.1.1 - - play.google.com 192.168.1.1 None - tenant.content_filter_denied DENIED \"Shopping;Software Downloads\" - 0 DENIED unknown - ssl play.google.com 443 - - 192.168.1.1 0 0 - \"none\" \"none\" none - - high *.google.com \"Search Engines/Portals\" unavailable unavailable Transparent \"WA-LS-D_Standard-Deny2\" 192.168.1.1 high TLSv1.2 -\r\n2018-02-02 18:31:16 1 192.168.1.1 - - play.google.com 192.168.1.1 None - tenant.content_filter_denied DENIED \"Shopping;Software Downloads\" - 0 DENIED unknown - ssl play.google.com 443 - - 192.168.1.1 0 0 - \"none\" \"none\" none - - high *.google.com \"Search Engines/Portals\" unavailable unavailable Transparent \"WA-LS-D_Standard-Deny2\" 192.168.1.1 high TLSv1.2 -\r\n2018-02-02 18:31:16 1 192.168.1.1 - - play.google.com 192.168.1.1 None - tenant.content_filter_denied DENIED \"Shopping;Software Downloads\" - 0 DENIED unknown - ssl play.google.com 443 - - 192.168.1.1 0 0 - \"none\" \"none\" none - - high *.google.com \"Search Engines/Portals\" unavailable unavailable Transparent \"WA-LS-D_Standard-Deny2\" 192.168.1.1 high TLSv1.2 -\r\n2018-02-02 18:31:16 1 192.168.1.1 - - play.google.com 192.168.1.1 None - tenant.content_filter_denied DENIED \"Shopping;Software Downloads\" - 0 DENIED unknown - ssl play.google.com 443 - - 192.168.1.1 0 0 - \"none\" \"none\" none - - high *.google.com \"Search Engines/Portals\" unavailable unavailable Transparent \"WA-LS-D_Standard-Deny2\" 192.168.1.1 high TLSv1.2 -\r\n2018-02-02 18:31:16 1 192.168.1.1 - - play.google.com 192.168.1.1 None - tenant.content_filter_denied DENIED \"Shopping;Software Downloads\" - 0 DENIED unknown - ssl play.google.com 443 - - 192.168.1.1 0 0 - \"none\" \"none\" none - - high *.google.com \"Search Engines/Portals\" unavailable unavailable Transparent \"WA-LS-D_Standard-Deny2\" 192.168.1.1 high TLSv1 -\r\n2018-02-02 18:31:16 1 192.168.1.1 - - play.google.com 192.168.1.1 None - tenant.content_filter_denied DENIED \"Shopping;Software Downloads\" - 0 DENIED unknown - ssl play.google.com 443 - - 192.168.1.1 0 0 - \"none\" \"none\" none - - high *.google.com \"Search Engines/Portals\" unavailable unavailable Transparent \"WA-LS-D_Standard-Deny2\" 192.168.1.1 high TLSv1 -\r\n2018-02-02 18:31:16 1 192.168.1.1 - - play.google.com 192.168.1.1 None - tenant.content_filter_denied DENIED \"Shopping;Software Downloads\" - 0 DENIED unknown - ssl play.google.com 443 - - 192.168.1.1 0 0 - \"none\" \"none\" none - - high *.google.com \"Search Engines/Portals\" unavailable unavailable Transparent \"WA-LS-D_Standard-Deny2\" 192.168.1.1 high TLSv1.2 -\r\n2018-02-02 18:31:16 1 192.168.1.1 - - play.google.com 192.168.1.1 None - tenant.content_filter_denied DENIED \"Shopping;Software Downloads\" - 0 DENIED unknown - ssl play.google.com 443 - - 192.168.1.1 0 0 - \"none\" \"none\" none - - high *.google.com \"Search Engines/Portals\" unavailable unavailable Transparent \"WA-LS-D_Standard-Deny2\" 192.168.1.1 high TLSv1.2 -\r\n2018-02-02 18:31:16 1 192.168.1.1 - - play.google.com 192.168.1.1 None - tenant.content_filter_denied DENIED \"Shopping;Software Downloads\" - 0 DENIED unknown - ssl play.google.com 443 - - 192.168.1.1 0 0 - \"none\" \"none\" none - - high *.google.com \"Search Engines/Portals\" unavailable unavailable Transparent \"WA-LS-D_Standard-Deny2\" 192.168.1.1 high TLSv1.2 -\r\n2018-02-02 18:31:18 1 192.168.1.1 - - play.google.com 192.168.1.1 None - tenant.content_filter_denied DENIED \"Shopping;Software Downloads\" - 0 DENIED unknown - ssl play.google.com 443 - - 192.168.1.1 0 0 - \"none\" \"none\" none - - high *.google.com \"Search Engines/Portals\" unavailable unavailable Transparent \"WA-LS-D_Standard-Deny2\" 192.168.1.1 high TLSv1.2 -\r\n2018-02-02 18:31:18 1 192.168.1.1 - - play.google.com 192.168.1.1 None - tenant.content_filter_denied DENIED \"Shopping;Software Downloads\" - 0 DENIED unknown - ssl play.google.com 443 - - 192.168.1.1 0 0 - \"none\" \"none\" none - - high *.google.com \"Search Engines/Portals\" unavailable unavailable Transparent \"WA-LS-D_Standard-Deny2\" 192.168.1.1 high TLSv1 -\r\n2018-02-02 18:31:18 1 192.168.1.1 - - play.google.com 192.168.1.1 None - tenant.content_filter_denied DENIED \"Shopping;Software Downloads\" - 0 DENIED unknown - ssl play.google.com 443 - - 192.168.1.1 0 0 - \"none\" \"none\" none - - high *.google.com \"Search Engines/Portals\" unavailable unavailable Transparent \"WA-LS-D_Standard-Deny2\" 192.168.1.1 high TLSv1 -\r\n2018-02-02 18:31:18 1 192.168.1.1 - - nqs-nl1-c2.example.com 192.168.1.1 None - tenant.content_filter_denied DENIED \"Business/Economy;Web Ads/Analytics\" - 0 DENIED unknown - ssl nqs-nl1-c2.example.com 443 - - 192.168.1.1 0 0 - \"none\" \"none\" none - - high *.example.com \"Business/Economy\" unavailable unavailable Transparent \"WA-LS-D_Standard-Deny2\" 192.168.1.1 high TLSv1 -\r\n2018-02-02 18:31:18 1 192.168.1.1 - - otf.msn.com 192.168.1.1 None - tenant.content_filter_denied DENIED \"Web Ads/Analytics\" - 0 DENIED unknown - ssl otf.msn.com 443 - - 192.168.1.1 0 0 - \"none\" \"none\" none - - high udc.msn.com \"Search Engines/Portals\" unavailable unavailable Transparent \"WA-LS-D_Standard-Deny2\" 192.168.1.1 high TLSv1.2 -\r\n2018-02-02 18:31:18 1 192.168.1.1 - - otf.msn.com 192.168.1.1 None - tenant.content_filter_denied DENIED \"Web Ads/Analytics\" - 0 DENIED unknown - ssl otf.msn.com 443 - - 192.168.1.1 0 0 - \"none\" \"none\" none - - high udc.msn.com \"Search Engines/Portals\" unavailable unavailable Transparent \"WA-LS-D_Standard-Deny2\" 192.168.1.1 high TLSv1.2 -\r\n2018-02-02 18:31:18 1 192.168.1.1 - - cont-5.p-cdn.us 192.168.1.1 None - tenant.content_filter_denied DENIED \"none\" - 0 DENIED unknown - ssl cont-5.p-cdn.us 443 - - 192.168.1.1 0 0 - \"none\" \"none\" none - - high *.p-cdn.us \"none\" unavailable unavailable Transparent \"WA-SP-D_Cat-None\" 192.168.1.1 high TLSv1 -\r\n2018-02-02 18:31:18 1 192.168.1.1 - - cont-5.p-cdn.us 192.168.1.1 None - tenant.content_filter_denied DENIED \"none\" - 0 DENIED unknown - ssl cont-5.p-cdn.us 443 - - 192.168.1.1 0 0 - \"none\" \"none\" none - - high *.p-cdn.us \"none\" unavailable unavailable Transparent \"WA-SP-D_Cat-None\" 192.168.1.1 high TLSv1 -\r\n2018-02-02 18:31:18 1 192.168.1.1 - - nqs-nl1-c2.example.com 192.168.1.1 None - tenant.content_filter_denied DENIED \"Business/Economy;Web Ads/Analytics\" - 0 DENIED unknown - ssl nqs-nl1-c2.example.com 443 - - 192.168.1.1 0 0 - \"none\" \"none\" none - - high *.example.com \"Business/Economy\" unavailable unavailable Transparent \"WA-LS-D_Standard-Deny2\" 192.168.1.1 high TLSv1.2 -\r\n2018-02-02 18:31:18 1 192.168.1.1 - - mssl.fwmrm.net 192.168.1.1 None - tenant.content_filter_denied DENIED \"Streaming_Video_Required_Analytics;Web Ads/Analytics\" - 0 DENIED unknown - ssl mssl.fwmrm.net 443 - - 192.168.1.1 0 0 - \"none\" \"none\" none - - high *.fwmrm.net \"Web Ads/Analytics\" unavailable unavailable Transparent \"WA-LS-D_Standard-Deny2\" 192.168.1.1 high TLSv1 -\r\n2018-02-02 18:31:18 1 192.168.1.1 - - mssl.fwmrm.net 192.168.1.1 None - tenant.content_filter_denied DENIED \"Streaming_Video_Required_Analytics;Web Ads/Analytics\" - 0 DENIED unknown - ssl mssl.fwmrm.net 443 - - 192.168.1.1 0 0 - \"none\" \"none\" none - - high *.fwmrm.net \"Web Ads/Analytics\" unavailable unavailable Transparent \"WA-LS-D_Standard-Deny2\" 192.168.1.1 high TLSv1 -\r\n2018-02-02 18:31:18 1 192.168.1.1 - - play.google.com 192.168.1.1 None - tenant.content_filter_denied DENIED \"Shopping;Software Downloads\" - 0 DENIED unknown - ssl play.google.com 443 - - 192.168.1.1 0 0 - \"none\" \"none\" none - - high *.google.com \"Search Engines/Portals\" unavailable unavailable Transparent \"WA-LS-D_Standard-Deny2\" 192.168.1.1 high TLSv1.2 -\r\n2018-02-02 18:31:18 1 192.168.1.1 - - play.google.com 192.168.1.1 None - tenant.content_filter_denied DENIED \"Shopping;Software Downloads\" - 0 DENIED unknown - ssl play.google.com 443 - - 192.168.1.1 0 0 - \"none\" \"none\" none - - high *.google.com \"Search Engines/Portals\" unavailable unavailable Transparent \"WA-LS-D_Standard-Deny2\" 192.168.1.1 high TLSv1.2 -\r\n2018-02-02 18:31:18 1 192.168.1.1 - - play.google.com 192.168.1.1 None - tenant.content_filter_denied DENIED \"Shopping;Software Downloads\" - 0 DENIED unknown - ssl play.google.com 443 - - 192.168.1.1 0 0 - \"none\" \"none\" none - - high *.google.com \"Search Engines/Portals\" unavailable unavailable Transparent \"WA-LS-D_Standard-Deny2\" 192.168.1.1 high TLSv1.2 -\r\n2018-02-02 18:31:18 1 192.168.1.1 - - cbsinteractive.hb.omtrdc.net 192.168.1.1 None - tenant.content_filter_denied DENIED \"Streaming_Video_Required_Analytics;Web Ads/Analytics\" - 0 DENIED unknown - ssl cbsinteractive.hb.omtrdc.net 443 - - 192.168.1.1 0 0 - \"none\" \"none\" none - - high *.hb.omtrdc.net \"Web Ads/Analytics\" unavailable unavailable Transparent \"WA-LS-D_Standard-Deny2\" 192.168.1.1 high TLSv1.2 -\r\n2018-02-02 18:31:18 1 192.168.1.1 - - cent.spots.im 192.168.1.1 None - tenant.content_filter_denied DENIED \"Web Ads/Analytics\" - 0 DENIED unknown - ssl cent.spots.im 443 - - 192.168.1.1 0 0 - \"none\" \"none\" none - - high *.spots.im \"Placeholders\" unavailable unavailable Transparent \"WA-LS-D_Standard-Deny2\" 192.168.1.1 high TLSv1.2 -\r\n2018-02-02 18:31:18 1 192.168.1.1 - - cbsinteractive.hb.omtrdc.net 192.168.1.1 None - tenant.content_filter_denied DENIED \"Streaming_Video_Required_Analytics;Web Ads/Analytics\" - 0 DENIED unknown - ssl cbsinteractive.hb.omtrdc.net 443 - - 192.168.1.1 0 0 - \"none\" \"none\" none - - high *.hb.omtrdc.net \"Web Ads/Analytics\" unavailable unavailable Transparent \"WA-LS-D_Standard-Deny2\" 192.168.1.1 high TLSv1.2 -\r\n2018-02-02 18:31:18 1 192.168.1.1 - - otf.msn.com 192.168.1.1 None - tenant.content_filter_denied DENIED \"Web Ads/Analytics\" - 0 DENIED unknown - ssl otf.msn.com 443 - - 192.168.1.1 0 0 - \"none\" \"none\" none - - high udc.msn.com \"Search Engines/Portals\" unavailable unavailable Transparent \"WA-LS-D_Standard-Deny2\" 192.168.1.1 high TLSv1.2 -\r\n2018-02-02 18:31:18 1 192.168.1.1 - - play.google.com 192.168.1.1 None - tenant.content_filter_denied DENIED \"Shopping;Software Downloads\" - 0 DENIED unknown - ssl play.google.com 443 - - 192.168.1.1 0 0 - \"none\" \"none\" none - - high *.google.com \"Search Engines/Portals\" unavailable unavailable Transparent \"WA-LS-D_Standard-Deny2\" 192.168.1.1 high TLSv1.2 -\r\n2018-02-02 18:31:18 1 192.168.1.1 - - play.google.com 192.168.1.1 None - tenant.content_filter_denied DENIED \"Shopping;Software Downloads\" - 0 DENIED unknown - ssl play.google.com 443 - - 192.168.1.1 0 0 - \"none\" \"none\" none - - high *.google.com \"Search Engines/Portals\" unavailable unavailable Transparent \"WA-LS-D_Standard-Deny2\" 192.168.1.1 high TLSv1.2 -\r\n2018-02-02 18:31:18 1 192.168.1.1 - - play.google.com 192.168.1.1 None - tenant.content_filter_denied DENIED \"Shopping;Software Downloads\" - 0 DENIED unknown - ssl play.google.com 443 - - 192.168.1.1 0 0 - \"none\" \"none\" none - - high *.google.com \"Search Engines/Portals\" unavailable unavailable Transparent \"WA-LS-D_Standard-Deny2\" 192.168.1.1 high TLSv1.2 -\r\n2018-02-02 18:31:18 1 192.168.1.1 - - play.google.com 192.168.1.1 None - tenant.content_filter_denied DENIED \"Shopping;Software Downloads\" - 0 DENIED unknown - ssl play.google.com 443 - - 192.168.1.1 0 0 - \"none\" \"none\" none - - high *.google.com \"Search Engines/Portals\" unavailable unavailable Transparent \"WA-LS-D_Standard-Deny2\" 192.168.1.1 high TLSv1.2 -\r\n2018-02-02 18:31:18 1 192.168.1.1 - - play.google.com 192.168.1.1 None - tenant.content_filter_denied DENIED \"Shopping;Software Downloads\" - 0 DENIED unknown - ssl play.google.com 443 - - 192.168.1.1 0 0 - \"none\" \"none\" none - - high *.google.com \"Search Engines/Portals\" unavailable unavailable Transparent \"WA-LS-D_Standard-Deny2\" 192.168.1.1 high TLSv1.2 -\r\n2018-02-02 18:31:18 1 192.168.1.1 - - play.google.com 192.168.1.1 None - tenant.content_filter_denied DENIED \"Shopping;Software Downloads\" - 0 DENIED unknown - ssl play.google.com 443 - - 192.168.1.1 0 0 - \"none\" \"none\" none - - high *.google.com \"Search Engines/Portals\" unavailable unavailable Transparent \"WA-LS-D_Standard-Deny2\" 192.168.1.1 high TLSv1 -\r\n2018-02-02 18:31:18 1 192.168.1.1 - - play.google.com 192.168.1.1 None - tenant.content_filter_denied DENIED \"Shopping;Software Downloads\" - 0 DENIED unknown - ssl play.google.com 443 - - 192.168.1.1 0 0 - \"none\" \"none\" none - - high *.google.com \"Search Engines/Portals\" unavailable unavailable Transparent \"WA-LS-D_Standard-Deny2\" 192.168.1.1 high TLSv1 -\r\n2018-02-02 18:31:18 196 192.168.1.1 - - client.wns.windows.com 192.168.1.1 None - - OBSERVED \"Technology/Internet\" - 0 TUNNELED unknown - ssl client.wns.windows.com 443 - - 192.168.1.1 332 1692 - \"none\" \"none\" none - - high *.wns.windows.com \"Technology/Internet\" unavailable unavailable Transparent \"WA-SP-A_Standard-Allow\" 192.168.1.1 high TLSv1.2 -\r\n2018-02-02 18:31:18 1 192.168.1.1 - - otf.msn.com 192.168.1.1 None - tenant.content_filter_denied DENIED \"Web Ads/Analytics\" - 0 DENIED unknown - ssl otf.msn.com 443 - - 192.168.1.1 0 0 - \"none\" \"none\" none - - high udc.msn.com \"Search Engines/Portals\" unavailable unavailable Transparent \"WA-LS-D_Standard-Deny2\" 192.168.1.1 high TLSv1 -\r\n2018-02-02 18:31:18 1 192.168.1.1 - - play.google.com 192.168.1.1 None - tenant.content_filter_denied DENIED \"Shopping;Software Downloads\" - 0 DENIED unknown - ssl play.google.com 443 - - 192.168.1.1 0 0 - \"none\" \"none\" none - - high *.google.com \"Search Engines/Portals\" unavailable unavailable Transparent \"WA-LS-D_Standard-Deny2\" 192.168.1.1 high TLSv1.2 -\r\n2018-02-02 18:31:18 1 192.168.1.1 - - nqs-nl1-c2.example.com 192.168.1.1 None - tenant.content_filter_denied DENIED \"Business/Economy;Web Ads/Analytics\" - 0 DENIED unknown - ssl nqs-nl1-c2.example.com 443 - - 192.168.1.1 0 0 - \"none\" \"none\" none - - high *.example.com \"Business/Economy\" unavailable unavailable Transparent \"WA-LS-D_Standard-Deny2\" 192.168.1.1 high TLSv1 -\r\n2018-02-02 18:31:18 1 192.168.1.1 - - s.mnet-ad.net 192.168.1.1 None - tenant.content_filter_denied DENIED \"Web Ads/Analytics\" - 0 DENIED unknown - ssl s.mnet-ad.net 443 - - 192.168.1.1 0 0 - \"none\" \"none\" none - - high *.mnet-ad.net \"Web Ads/Analytics\" unavailable unavailable Transparent \"WA-LS-D_Standard-Deny2\" 192.168.1.1 high TLSv1.2 -\r\n2018-02-02 18:31:18 1 192.168.1.1 - - s.mnet-ad.net 192.168.1.1 None - tenant.content_filter_denied DENIED \"Web Ads/Analytics\" - 0 DENIED unknown - ssl s.mnet-ad.net 443 - - 192.168.1.1 0 0 - \"none\" \"none\" none - - high *.mnet-ad.net \"Web Ads/Analytics\" unavailable unavailable Transparent \"WA-LS-D_Standard-Deny2\" 192.168.1.1 high TLSv1.2 -\r\n2018-02-02 18:31:18 1 192.168.1.1 - - otf.msn.com 192.168.1.1 None - tenant.content_filter_denied DENIED \"Web Ads/Analytics\" - 0 DENIED unknown - ssl otf.msn.com 443 - - 192.168.1.1 0 0 - \"none\" \"none\" none - - high udc.msn.com \"Search Engines/Portals\" unavailable unavailable Transparent \"WA-LS-D_Standard-Deny2\" 192.168.1.1 high TLSv1 -\r\n2018-02-02 18:31:18 1 192.168.1.1 - - otf.msn.com 192.168.1.1 None - tenant.content_filter_denied DENIED \"Web Ads/Analytics\" - 0 DENIED unknown - ssl otf.msn.com 443 - - 192.168.1.1 0 0 - \"none\" \"none\" none - - high udc.msn.com \"Search Engines/Portals\" unavailable unavailable Transparent \"WA-LS-D_Standard-Deny2\" 192.168.1.1 high TLSv1 -\r\n2018-02-02 18:31:18 1 192.168.1.1 - - play.google.com 192.168.1.1 None - tenant.content_filter_denied DENIED \"Shopping;Software Downloads\" - 0 DENIED unknown - ssl play.google.com 443 - - 192.168.1.1 0 0 - \"none\" \"none\" none - - high *.google.com \"Search Engines/Portals\" unavailable unavailable Transparent \"WA-LS-D_Standard-Deny2\" 192.168.1.1 high TLSv1.2 -\r\n2018-02-02 18:31:58 1 192.168.1.1 - - play.google.com 192.168.1.1 None - tenant.content_filter_denied DENIED \"Shopping;Software Downloads\" - 0 DENIED unknown - ssl play.google.com 443 - - 192.168.1.1 0 0 - \"none\" \"none\" none - - high *.google.com \"Search Engines/Portals\" unavailable unavailable Transparent \"WA-LS-D_Standard-Deny2\" 192.168.1.1 high TLSv1 -\r\n2018-02-02 18:31:58 1 192.168.1.1 - - play.google.com 192.168.1.1 None - tenant.content_filter_denied DENIED \"Shopping;Software Downloads\" - 0 DENIED unknown - ssl play.google.com 443 - - 192.168.1.1 0 0 - \"none\" \"none\" none - - high *.google.com \"Search Engines/Portals\" unavailable unavailable Transparent \"WA-LS-D_Standard-Deny2\" 192.168.1.1 high TLSv1 -\r\n2018-02-02 18:31:58 1 192.168.1.1 - - play.google.com 192.168.1.1 None - tenant.content_filter_denied DENIED \"Shopping;Software Downloads\" - 0 DENIED unknown - ssl play.google.com 443 - - 192.168.1.1 0 0 - \"none\" \"none\" none - - high *.google.com \"Search Engines/Portals\" unavailable unavailable Transparent \"WA-LS-D_Standard-Deny2\" 192.168.1.1 high TLSv1 -\r\n2018-02-02 18:31:58 1 192.168.1.1 - - otf.msn.com 192.168.1.1 None - tenant.content_filter_denied DENIED \"Web Ads/Analytics\" - 0 DENIED unknown - ssl otf.msn.com 443 - - 192.168.1.1 0 0 - \"none\" \"none\" none - - high udc.msn.com \"Search Engines/Portals\" unavailable unavailable Transparent \"WA-LS-D_Standard-Deny2\" 192.168.1.1 high TLSv1 -\r\n2018-02-02 18:31:58 1 192.168.1.1 - - otf.msn.com 192.168.1.1 None - tenant.content_filter_denied DENIED \"Web Ads/Analytics\" - 0 DENIED unknown - ssl otf.msn.com 443 - - 192.168.1.1 0 0 - \"none\" \"none\" none - - high udc.msn.com \"Search Engines/Portals\" unavailable unavailable Transparent \"WA-LS-D_Standard-Deny2\" 192.168.1.1 high TLSv1 -\r\n2018-02-02 18:31:58 1 192.168.1.1 - - play.google.com 192.168.1.1 None - tenant.content_filter_denied DENIED \"Shopping;Software Downloads\" - 0 DENIED unknown - ssl play.google.com 443 - - 192.168.1.1 0 0 - \"none\" \"none\" none - - high *.google.com \"Search Engines/Portals\" unavailable unavailable Transparent \"WA-LS-D_Standard-Deny2\" 192.168.1.1 high TLSv1.2 -\r\n2018-02-02 18:31:58 615 192.168.1.1 - - client.wns.windows.com 192.168.1.1 None - - OBSERVED \"Technology/Internet\" - 0 TUNNELED unknown - ssl client.wns.windows.com 443 - - 192.168.1.1 332 1669 - \"none\" \"none\" none - - high *.wns.windows.com \"Technology/Internet\" unavailable unavailable Transparent \"WA-SP-A_Standard-Allow\" 192.168.1.1 high TLSv1.2 -\r\n2018-02-02 18:31:58 1 192.168.1.1 - - sb.scorecardresearch.com 192.168.1.1 None - tenant.content_filter_denied DENIED \"Web Ads/Analytics\" - 0 DENIED unknown - ssl sb.scorecardresearch.com 443 - - 192.168.1.1 0 0 - \"none\" \"none\" none - - high *.scorecardresearch.com \"Business/Economy\" unavailable unavailable Transparent \"WA-LS-D_Standard-Deny2\" 192.168.1.1 high TLSv1.2 -\r\n2018-02-02 18:31:58 271 192.168.1.1 - - client.wns.windows.com 192.168.1.1 None - - OBSERVED \"Technology/Internet\" - 0 TUNNELED unknown - ssl client.wns.windows.com 443 - - 192.168.1.1 332 1704 - \"none\" \"none\" none - - high *.wns.windows.com \"Technology/Internet\" unavailable unavailable Transparent \"WA-SP-A_Standard-Allow\" 192.168.1.1 high TLSv1.2 -\r\n2018-02-02 18:31:58 1 192.168.1.1 - - play.google.com 192.168.1.1 None - tenant.content_filter_denied DENIED \"Shopping;Software Downloads\" - 0 DENIED unknown - ssl play.google.com 443 - - 192.168.1.1 0 0 - \"none\" \"none\" none - - high *.google.com \"Search Engines/Portals\" unavailable unavailable Transparent \"WA-LS-D_Standard-Deny2\" 192.168.1.1 high TLSv1.2 -\r\n2018-02-02 18:31:58 31946 192.168.1.1 - - api.spotify.com 192.168.1.1 None - - OBSERVED \"Radio/Audio Streams;Entertainment\" - 0 TUNNELED unknown - ssl api.spotify.com 443 - - 192.168.1.1 2573 3479 - \"none\" \"none\" none - - high *.spotify.com \"Radio/Audio Streams\" unavailable unavailable Transparent \"WA-SP-A_Standard-Allow\" 192.168.1.1 high TLSv1.2 -\r\n2018-02-02 18:31:58 33207 192.168.1.1 - - open.spotify.com 192.168.1.1 None - - OBSERVED \"Radio/Audio Streams;Entertainment\" - 0 TUNNELED unknown - ssl open.spotify.com 443 - - 192.168.1.1 2075 2976 - \"none\" \"none\" none - - high *.spotify.com \"Radio/Audio Streams\" unavailable unavailable Transparent \"WA-SP-A_Standard-Allow\" 192.168.1.1 high TLSv1.2 -\r\n2018-02-02 18:31:58 32020 192.168.1.1 - - api.spotify.com 192.168.1.1 None - - OBSERVED \"Radio/Audio Streams;Entertainment\" - 0 TUNNELED unknown - ssl api.spotify.com 443 - - 192.168.1.1 1842 1302 - \"none\" \"none\" none - - high *.spotify.com \"Radio/Audio Streams\" unavailable unavailable Transparent \"WA-SP-A_Standard-Allow\" 192.168.1.1 high TLSv1.2 -\r\n2018-02-02 18:31:58 1 192.168.1.1 - - www.google-analytics.com 192.168.1.1 None - tenant.content_filter_denied DENIED \"Web Ads/Analytics\" - 0 DENIED unknown - ssl www.google-analytics.com 443 - - 192.168.1.1 0 0 - \"none\" \"none\" none - - high *.google-analytics.com \"Web Ads/Analytics\" unavailable unavailable Transparent \"WA-LS-D_Standard-Deny2\" 192.168.1.1 high TLSv1 -\r\n2018-02-02 18:31:58 1 192.168.1.1 - - play.google.com 192.168.1.1 None - tenant.content_filter_denied DENIED \"Shopping;Software Downloads\" - 0 DENIED unknown - ssl play.google.com 443 - - 192.168.1.1 0 0 - \"none\" \"none\" none - - high *.google.com \"Search Engines/Portals\" unavailable unavailable Transparent \"WA-LS-D_Standard-Deny2\" 192.168.1.1 high TLSv1 -\r\n2018-02-02 18:31:58 1 192.168.1.1 - - play.google.com 192.168.1.1 None - tenant.content_filter_denied DENIED \"Shopping;Software Downloads\" - 0 DENIED unknown - ssl play.google.com 443 - - 192.168.1.1 0 0 - \"none\" \"none\" none - - high *.google.com \"Search Engines/Portals\" unavailable unavailable Transparent \"WA-LS-D_Standard-Deny2\" 192.168.1.1 high TLSv1 -\r\n2018-02-02 18:31:58 21086 192.168.1.1 - - db5sch101110105.wns.windows.com 192.168.1.1 None - - OBSERVED \"Technology/Internet\" - 0 TUNNELED unknown - ssl db5sch101110105.wns.windows.com 443 - - 192.168.1.1 129 550 - \"none\" \"none\" none - - high *.wns.windows.com \"Technology/Internet\" unavailable unavailable Transparent \"WA-SP-A_Standard-Allow\" 192.168.1.1 high TLSv1.2 -\r\n2018-02-02 18:31:59 188 192.168.1.1 - - client.wns.windows.com 192.168.1.1 None - - OBSERVED \"Technology/Internet\" - 0 TUNNELED unknown - ssl client.wns.windows.com 443 - - 192.168.1.1 332 1660 - \"none\" \"none\" none - - high *.wns.windows.com \"Technology/Internet\" unavailable unavailable Transparent \"WA-SP-A_Standard-Allow\" 192.168.1.1 high TLSv1.2 -\r\n2018-02-02 18:31:59 324 192.168.1.1 - - client.wns.windows.com 192.168.1.1 None - - OBSERVED \"Technology/Internet\" - 0 TUNNELED unknown - ssl client.wns.windows.com 443 - - 192.168.1.1 332 1680 - \"none\" \"none\" none - - high *.wns.windows.com \"Technology/Internet\" unavailable unavailable Transparent \"WA-SP-A_Standard-Allow\" 192.168.1.1 high TLSv1.2 -\r\n2018-02-02 18:31:59 1 192.168.1.1 - - play.google.com 192.168.1.1 None - tenant.content_filter_denied DENIED \"Shopping;Software Downloads\" - 0 DENIED unknown - ssl play.google.com 443 - - 192.168.1.1 0 0 - \"none\" \"none\" none - - high *.google.com \"Search Engines/Portals\" unavailable unavailable Transparent \"WA-LS-D_Standard-Deny2\" 192.168.1.1 high TLSv1 -\r\n2018-02-02 18:31:59 1 192.168.1.1 - - play.google.com 192.168.1.1 None - tenant.content_filter_denied DENIED \"Shopping;Software Downloads\" - 0 DENIED unknown - ssl play.google.com 443 - - 192.168.1.1 0 0 - \"none\" \"none\" none - - high *.google.com \"Search Engines/Portals\" unavailable unavailable Transparent \"WA-LS-D_Standard-Deny2\" 192.168.1.1 high TLSv1.2 -\r\n2018-02-02 18:31:59 1 192.168.1.1 - - play.google.com 192.168.1.1 None - tenant.content_filter_denied DENIED \"Shopping;Software Downloads\" - 0 DENIED unknown - ssl play.google.com 443 - - 192.168.1.1 0 0 - \"none\" \"none\" none - - high *.google.com \"Search Engines/Portals\" unavailable unavailable Transparent \"WA-LS-D_Standard-Deny2\" 192.168.1.1 high TLSv1 -\r\n2018-02-02 18:31:59 2 192.168.1.1 - - play.google.com 192.168.1.1 None - tenant.content_filter_denied DENIED \"Shopping;Software Downloads\" - 0 DENIED unknown - ssl play.google.com 443 - - 192.168.1.1 0 0 - \"none\" \"none\" none - - high *.google.com \"Search Engines/Portals\" unavailable unavailable Transparent \"WA-LS-D_Standard-Deny2\" 192.168.1.1 high TLSv1.2 -\r\n2018-02-02 18:31:59 1 192.168.1.1 - - play.google.com 192.168.1.1 None - tenant.content_filter_denied DENIED \"Shopping;Software Downloads\" - 0 DENIED unknown - ssl play.google.com 443 - - 192.168.1.1 0 0 - \"none\" \"none\" none - - high *.google.com \"Search Engines/Portals\" unavailable unavailable Transparent \"WA-LS-D_Standard-Deny2\" 192.168.1.1 high TLSv1 -\r\n2018-02-02 18:31:59 1 192.168.1.1 - - play.google.com 192.168.1.1 None - tenant.content_filter_denied DENIED \"Shopping;Software Downloads\" - 0 DENIED unknown - ssl play.google.com 443 - - 192.168.1.1 0 0 - \"none\" \"none\" none - - high *.google.com \"Search Engines/Portals\" unavailable unavailable Transparent \"WA-LS-D_Standard-Deny2\" 192.168.1.1 high TLSv1 -\r\n2018-02-02 18:31:59 1 192.168.1.1 - - oneclient.sfx.ms 192.168.1.1 None - tenant.content_filter_denied DENIED \"File Storage/Sharing\" - 0 DENIED unknown - ssl oneclient.sfx.ms 443 - - 192.168.1.1 0 0 - \"Windows Live SkyDrive\" - none - - high wildcard.sfx.ms \"Content Servers\" unavailable unavailable Transparent \"WA-LS-D_Standard-Deny2\" 192.168.1.1 high TLSv1.2 -\r\n2018-02-02 18:31:59 3453 192.168.1.1 - - db5sch103091510.wns.windows.com 192.168.1.1 None - - OBSERVED \"Technology/Internet\" - 0 TUNNELED unknown - ssl db5sch103091510.wns.windows.com 443 - - 192.168.1.1 129 550 - \"none\" \"none\" none - - high *.wns.windows.com \"Technology/Internet\" unavailable unavailable Transparent \"WA-SP-A_Standard-Allow\" 192.168.1.1 high TLSv1.2 -\r\n2018-02-02 18:31:59 1 192.168.1.1 - - play.google.com 192.168.1.1 None - tenant.content_filter_denied DENIED \"Shopping;Software Downloads\" - 0 DENIED unknown - ssl play.google.com 443 - - 192.168.1.1 0 0 - \"none\" \"none\" none - - high *.google.com \"Search Engines/Portals\" unavailable unavailable Transparent \"WA-LS-D_Standard-Deny2\" 192.168.1.1 high TLSv1.2 -\r\n2018-02-02 18:31:59 421 192.168.1.1 - - db5sch103091510.wns.windows.com 192.168.1.1 None - - OBSERVED \"Technology/Internet\" - 0 TUNNELED unknown - ssl db5sch103091510.wns.windows.com 443 - - 192.168.1.1 129 555 - \"none\" \"none\" none - - high *.wns.windows.com \"Technology/Internet\" unavailable unavailable Transparent \"WA-SP-A_Standard-Allow\" 192.168.1.1 high TLSv1.2 -\r\n2018-02-02 18:31:59 1 192.168.1.1 - - www.google-analytics.com 192.168.1.1 None - tenant.content_filter_denied DENIED \"Web Ads/Analytics\" - 0 DENIED unknown - ssl www.google-analytics.com 443 - - 192.168.1.1 0 0 - \"none\" \"none\" none - - high *.google-analytics.com \"Web Ads/Analytics\" unavailable unavailable Transparent \"WA-LS-D_Standard-Deny2\" 192.168.1.1 high TLSv1.2 -\r\n2018-02-02 18:31:59 1 192.168.1.1 - - play.google.com 192.168.1.1 None - tenant.content_filter_denied DENIED \"Shopping;Software Downloads\" - 0 DENIED unknown - ssl play.google.com 443 - - 192.168.1.1 0 0 - \"none\" \"none\" none - - high *.google.com \"Search Engines/Portals\" unavailable unavailable Transparent \"WA-LS-D_Standard-Deny2\" 192.168.1.1 high TLSv1.2 -\r\n2018-02-02 18:31:59 289 192.168.1.1 - - browser.pipe.aria.microsoft.com 192.168.1.1 None - - OBSERVED \"IA-Global-Permit;Technology/Internet\" - 0 TUNNELED unknown - ssl browser.pipe.aria.microsoft.com 443 - - 192.168.1.1 0 0 - \"none\" \"none\" none - - high *.pipe.aria.microsoft.com \"Technology/Internet\" unavailable unavailable Transparent \"WA-LS-A_Global-Exceptions\" 192.168.1.1 high TLSv1.2 -\r\n2018-02-02 18:31:59 8488 192.168.1.1 - - db5sch103102311.wns.windows.com 192.168.1.1 None - - OBSERVED \"Technology/Internet\" - 0 TUNNELED unknown - ssl db5sch103102311.wns.windows.com 443 - - 192.168.1.1 129 549 - \"none\" \"none\" none - - high *.wns.windows.com \"Technology/Internet\" unavailable unavailable Transparent \"WA-SP-A_Standard-Allow\" 192.168.1.1 high TLSv1.2 -\r\n2018-02-02 18:31:59 376 192.168.1.1 - - client.wns.windows.com 192.168.1.1 None - - OBSERVED \"Technology/Internet\" - 0 TUNNELED unknown - ssl client.wns.windows.com 443 - - 192.168.1.1 332 1668 - \"none\" \"none\" none - - high *.wns.windows.com \"Technology/Internet\" unavailable unavailable Transparent \"WA-SP-A_Standard-Allow\" 192.168.1.1 high TLSv1.2 -\r\n2018-02-02 18:31:59 1 192.168.1.1 - - col.eum-appdynamics.com 192.168.1.1 None - tenant.content_filter_denied DENIED \"Web Ads/Analytics\" - 0 DENIED unknown - ssl col.eum-appdynamics.com 443 - - 192.168.1.1 0 0 - \"none\" \"none\" none - - high *.eum-appdynamics.com \"Web Ads/Analytics\" unavailable unavailable Transparent \"WA-LS-D_Standard-Deny2\" 192.168.1.1 high TLSv1 -\r\n2018-02-02 18:31:59 238 192.168.1.1 - - client.wns.windows.com 192.168.1.1 None - - OBSERVED \"Technology/Internet\" - 0 TUNNELED unknown - ssl client.wns.windows.com 443 - - 192.168.1.1 332 1706 - \"none\" \"none\" none - - high *.wns.windows.com \"Technology/Internet\" unavailable unavailable Transparent \"WA-SP-A_Standard-Allow\" 192.168.1.1 high TLSv1.2 -\r\n2018-02-02 18:31:59 254 192.168.1.1 - - browser.pipe.aria.microsoft.com 192.168.1.1 None - - OBSERVED \"IA-Global-Permit;Technology/Internet\" - 0 TUNNELED unknown - ssl browser.pipe.aria.microsoft.com 443 - - 192.168.1.1 0 0 - \"none\" \"none\" none - - high *.pipe.aria.microsoft.com \"Technology/Internet\" unavailable unavailable Transparent \"WA-LS-A_Global-Exceptions\" 192.168.1.1 high TLSv1.2 -\r\n2018-02-02 18:31:59 15460 192.168.1.1 - - db5sch103090914.wns.windows.com 192.168.1.1 None - - OBSERVED \"Technology/Internet\" - 0 TUNNELED unknown - ssl db5sch103090914.wns.windows.com 443 - - 192.168.1.1 129 524 - \"none\" \"none\" none - - high *.wns.windows.com \"Technology/Internet\" unavailable unavailable Transparent \"WA-SP-A_Standard-Allow\" 192.168.1.1 high TLSv1.2 -\r\n2018-02-02 18:31:59 6360 192.168.1.1 - - db6sch102091603.wns.windows.com 192.168.1.1 None - - OBSERVED \"Technology/Internet\" - 0 TUNNELED unknown - ssl db6sch102091603.wns.windows.com 443 - - 192.168.1.1 129 550 - \"none\" \"none\" none - - high *.wns.windows.com \"Technology/Internet\" unavailable unavailable Transparent \"WA-SP-A_Standard-Allow\" 192.168.1.1 high TLSv1.2 -\r\n2018-02-02 18:31:59 1 192.168.1.1 - - api.cloudconnect.envisionware.net 192.168.1.1 None - tenant.content_filter_denied DENIED \"none\" - 0 DENIED unknown - ssl api.cloudconnect.envisionware.net 443 - - 192.168.1.1 0 0 - \"none\" \"none\" none - - high *.cloudconnect.envisionware.net \"none\" unavailable unavailable Transparent \"WA-SP-D_Cat-None\" 192.168.1.1 high TLSv1.2 -\r\n2018-02-02 18:31:59 10713 192.168.1.1 - - fonts.gstatic.com 192.168.1.1 None - - OBSERVED \"Search Engines/Portals\" - 0 TUNNELED unknown - ssl fonts.gstatic.com 443 - - 192.168.1.1 4327 93 - \"none\" \"none\" none - - high *.google.com \"Search Engines/Portals\" unavailable unavailable Transparent \"WA-SP-A_Standard-Allow\" 192.168.1.1 high TLSv1.2 -\r\n2018-02-02 18:31:59 1 192.168.1.1 - - datacloud.tealiumiq.com 192.168.1.1 None - tenant.content_filter_denied DENIED \"Web Ads/Analytics\" - 0 DENIED unknown - ssl datacloud.tealiumiq.com 443 - - 192.168.1.1 0 0 - \"none\" \"none\" none - - high *.tealiumiq.com \"Business/Economy\" unavailable unavailable Transparent \"WA-LS-D_Standard-Deny2\" 192.168.1.1 high TLSv1.2 -\r\n2018-02-02 18:31:59 1 192.168.1.1 - - datacloud.tealiumiq.com 192.168.1.1 None - tenant.content_filter_denied DENIED \"Web Ads/Analytics\" - 0 DENIED unknown - ssl datacloud.tealiumiq.com 443 - - 192.168.1.1 0 0 - \"none\" \"none\" none - - high *.tealiumiq.com \"Business/Economy\" unavailable unavailable Transparent \"WA-LS-D_Standard-Deny2\" 192.168.1.1 high TLSv1.2 -\r\n2018-02-02 18:31:59 1 192.168.1.1 - - play.google.com 192.168.1.1 None - tenant.content_filter_denied DENIED \"Shopping;Software Downloads\" - 0 DENIED unknown - ssl play.google.com 443 - - 192.168.1.1 0 0 - \"none\" \"none\" none - - high *.google.com \"Search Engines/Portals\" unavailable unavailable Transparent \"WA-LS-D_Standard-Deny2\" 192.168.1.1 high TLSv1.2 -\r\n2018-02-02 18:31:59 17587 192.168.1.1 - - db6sch102090309.wns.windows.com 192.168.1.1 None - - OBSERVED \"Technology/Internet\" - 0 TUNNELED unknown - ssl db6sch102090309.wns.windows.com 443 - - 192.168.1.1 129 554 - \"none\" \"none\" none - - high *.wns.windows.com \"Technology/Internet\" unavailable unavailable Transparent \"WA-SP-A_Standard-Allow\" 192.168.1.1 high TLSv1.2 -\r\n2018-02-02 18:31:59 14679 192.168.1.1 - - db5sch101102033.wns.windows.com 192.168.1.1 None - - OBSERVED \"Technology/Internet\" - 0 TUNNELED unknown - ssl db5sch101102033.wns.windows.com 443 - - 192.168.1.1 129 550 - \"none\" \"none\" none - - high *.wns.windows.com \"Technology/Internet\" unavailable unavailable Transparent \"WA-SP-A_Standard-Allow\" 192.168.1.1 high TLSv1.2 -\r\n2018-02-02 18:31:59 1 192.168.1.1 - - play.google.com 192.168.1.1 None - tenant.content_filter_denied DENIED \"Shopping;Software Downloads\" - 0 DENIED unknown - ssl play.google.com 443 - - 192.168.1.1 0 0 - \"none\" \"none\" none - - high *.google.com \"Search Engines/Portals\" unavailable unavailable Transparent \"WA-LS-D_Standard-Deny2\" 192.168.1.1 high TLSv1.2 -","expected":[{"x-virus-id":null,"cs-method":"unknown","cs-username":null,"cs-categories":"Shopping;Software Downloads","x-rs-ocsp-error":null,"s-supplier-failures":null,"x-bluecoat-application-name":"none","s-action":"DENIED","s-supplier-ip":"192.168.1.1","cs-uri-port":443,"x-cs-ocsp-error":null,"cs(Referer)":null,"sc-status":0,"x-rs-certificate-hostname-threat-risk":"unavailable","s-ip":"192.168.1.1","date":[2018,2,2],"sc-filter-result":"DENIED","cs-ip":"192.168.1.1","cs-host":"play.google.com","x-bluecoat-reference-id":"WA-LS-D_Standard-Deny2","x-cs-connection-negotiated-cipher-strength":"high","x-cs-connection-negotiated-ssl-version":"TLSv1.2","x-exception-id":"tenant.content_filter_denied","x-rs-certificate-hostname":"*.google.com","c-connect-type":"Transparent","x-rs-connection-negotiated-cipher-strength":"high","cs-uri-scheme":"ssl","cs-threat-risk":"unavailable","s-supplier-name":"play.google.com","cs-uri-extension":null,"sc-bytes":0,"x-bluecoat-application-operation":"none","rs(Content-Type)":null,"c-ip":"192.168.1.1","time-taken":1.0,"cs(User-Agent)":null,"cs-auth-group":null,"cs-bytes":0,"s-supplier-country":"None","time":[18,31,16],"x-rs-certificate-observed-errors":"none","x-rs-certificate-hostname-category":"Search Engines/Portals","cs(Accept-Language)":null},{"cs-method":"unknown","cs-ip":"192.168.1.1","x-rs-certificate-hostname":"*.google.com","cs-username":null,"x-rs-certificate-observed-errors":"none","sc-status":0,"c-ip":"192.168.1.1","x-virus-id":null,"s-supplier-failures":null,"sc-bytes":0,"cs-uri-scheme":"ssl","s-supplier-country":"None","cs-uri-port":443,"s-supplier-ip":"192.168.1.1","x-exception-id":"tenant.content_filter_denied","cs-uri-extension":null,"x-bluecoat-application-name":"none","x-rs-certificate-hostname-category":"Search Engines/Portals","x-cs-connection-negotiated-ssl-version":"TLSv1.2","x-bluecoat-reference-id":"WA-LS-D_Standard-Deny2","x-rs-connection-negotiated-cipher-strength":"high","s-supplier-name":"play.google.com","s-action":"DENIED","cs(User-Agent)":null,"rs(Content-Type)":null,"cs(Referer)":null,"cs-auth-group":null,"cs(Accept-Language)":null,"date":[2018,2,2],"s-ip":"192.168.1.1","cs-host":"play.google.com","x-cs-connection-negotiated-cipher-strength":"high","cs-threat-risk":"unavailable","x-cs-ocsp-error":null,"sc-filter-result":"DENIED","time":[18,31,16],"x-rs-ocsp-error":null,"time-taken":1.0,"x-rs-certificate-hostname-threat-risk":"unavailable","c-connect-type":"Transparent","x-bluecoat-application-operation":"none","cs-categories":"Shopping;Software Downloads","cs-bytes":0},{"cs-auth-group":null,"x-rs-certificate-hostname":"*.google.com","s-supplier-name":"play.google.com","c-ip":"192.168.1.1","cs(User-Agent)":null,"cs-uri-extension":null,"time":[18,31,16],"x-exception-id":"tenant.content_filter_denied","sc-filter-result":"DENIED","s-ip":"192.168.1.1","sc-bytes":0,"c-connect-type":"Transparent","date":[2018,2,2],"s-supplier-ip":"192.168.1.1","x-rs-connection-negotiated-cipher-strength":"high","sc-status":0,"x-bluecoat-application-name":"none","x-cs-connection-negotiated-cipher-strength":"high","cs-uri-scheme":"ssl","x-rs-certificate-hostname-category":"Search Engines/Portals","x-rs-certificate-hostname-threat-risk":"unavailable","s-action":"DENIED","cs-method":"unknown","s-supplier-failures":null,"x-bluecoat-application-operation":"none","cs-ip":"192.168.1.1","cs-categories":"Shopping;Software Downloads","x-virus-id":null,"x-cs-ocsp-error":null,"cs-threat-risk":"unavailable","x-bluecoat-reference-id":"WA-LS-D_Standard-Deny2","cs-uri-port":443,"cs(Accept-Language)":null,"rs(Content-Type)":null,"x-rs-certificate-observed-errors":"none","cs-bytes":0,"time-taken":1.0,"x-cs-connection-negotiated-ssl-version":"TLSv1.2","cs(Referer)":null,"s-supplier-country":"None","cs-host":"play.google.com","x-rs-ocsp-error":null,"cs-username":null},{"x-rs-certificate-hostname-category":"Search Engines/Portals","cs-uri-port":443,"s-supplier-country":"None","cs-uri-scheme":"ssl","cs-bytes":0,"sc-status":0,"x-exception-id":"tenant.content_filter_denied","x-rs-connection-negotiated-cipher-strength":"high","date":[2018,2,2],"x-cs-connection-negotiated-ssl-version":"TLSv1.2","cs(Referer)":null,"x-bluecoat-reference-id":"WA-LS-D_Standard-Deny2","sc-bytes":0,"rs(Content-Type)":null,"x-bluecoat-application-operation":"none","x-cs-connection-negotiated-cipher-strength":"high","x-rs-ocsp-error":null,"cs-method":"unknown","time":[18,31,16],"sc-filter-result":"DENIED","x-rs-certificate-hostname":"*.google.com","cs(Accept-Language)":null,"c-ip":"192.168.1.1","s-supplier-name":"play.google.com","cs-host":"play.google.com","time-taken":1.0,"cs-ip":"192.168.1.1","s-supplier-ip":"192.168.1.1","x-rs-certificate-observed-errors":"none","cs-categories":"Shopping;Software Downloads","s-supplier-failures":null,"cs-username":null,"x-rs-certificate-hostname-threat-risk":"unavailable","x-cs-ocsp-error":null,"s-ip":"192.168.1.1","cs-auth-group":null,"c-connect-type":"Transparent","x-virus-id":null,"cs-uri-extension":null,"s-action":"DENIED","x-bluecoat-application-name":"none","cs(User-Agent)":null,"cs-threat-risk":"unavailable"},{"sc-bytes":0,"cs-host":"play.google.com","cs-threat-risk":"unavailable","x-bluecoat-reference-id":"WA-LS-D_Standard-Deny2","s-supplier-country":"None","x-rs-certificate-hostname-category":"Search Engines/Portals","sc-filter-result":"DENIED","sc-status":0,"cs(User-Agent)":null,"cs-method":"unknown","cs-ip":"192.168.1.1","x-rs-certificate-observed-errors":"none","x-cs-ocsp-error":null,"x-rs-connection-negotiated-cipher-strength":"high","x-cs-connection-negotiated-ssl-version":"TLSv1.2","cs-uri-port":443,"s-supplier-failures":null,"cs-uri-scheme":"ssl","time-taken":1.0,"cs-username":null,"x-rs-ocsp-error":null,"date":[2018,2,2],"x-cs-connection-negotiated-cipher-strength":"high","rs(Content-Type)":null,"x-rs-certificate-hostname":"*.google.com","cs-uri-extension":null,"x-rs-certificate-hostname-threat-risk":"unavailable","s-supplier-name":"play.google.com","cs-bytes":0,"x-bluecoat-application-name":"none","s-action":"DENIED","time":[18,31,16],"s-ip":"192.168.1.1","cs(Referer)":null,"c-ip":"192.168.1.1","x-bluecoat-application-operation":"none","x-virus-id":null,"s-supplier-ip":"192.168.1.1","c-connect-type":"Transparent","cs-categories":"Shopping;Software Downloads","x-exception-id":"tenant.content_filter_denied","cs(Accept-Language)":null,"cs-auth-group":null},{"cs-method":"unknown","s-ip":"192.168.1.1","sc-status":0,"x-cs-connection-negotiated-cipher-strength":"high","cs-uri-scheme":"ssl","x-bluecoat-application-operation":"none","cs-host":"play.google.com","s-supplier-failures":null,"x-cs-connection-negotiated-ssl-version":"TLSv1.2","cs-threat-risk":"unavailable","x-cs-ocsp-error":null,"x-rs-certificate-observed-errors":"none","x-rs-ocsp-error":null,"time":[18,31,16],"cs-bytes":0,"sc-bytes":0,"c-connect-type":"Transparent","time-taken":1.0,"s-supplier-ip":"192.168.1.1","x-bluecoat-application-name":"none","s-supplier-country":"None","x-virus-id":null,"x-rs-certificate-hostname-threat-risk":"unavailable","x-exception-id":"tenant.content_filter_denied","x-rs-connection-negotiated-cipher-strength":"high","x-bluecoat-reference-id":"WA-LS-D_Standard-Deny2","date":[2018,2,2],"x-rs-certificate-hostname-category":"Search Engines/Portals","cs-ip":"192.168.1.1","cs(User-Agent)":null,"c-ip":"192.168.1.1","rs(Content-Type)":null,"s-supplier-name":"play.google.com","x-rs-certificate-hostname":"*.google.com","sc-filter-result":"DENIED","s-action":"DENIED","cs-auth-group":null,"cs-username":null,"cs-categories":"Shopping;Software Downloads","cs-uri-extension":null,"cs(Referer)":null,"cs(Accept-Language)":null,"cs-uri-port":443},{"cs(User-Agent)":null,"s-action":"DENIED","x-bluecoat-reference-id":"WA-LS-D_Standard-Deny2","x-cs-connection-negotiated-ssl-version":"TLSv1.2","cs-ip":"192.168.1.1","x-bluecoat-application-operation":"none","cs-uri-scheme":"ssl","cs-uri-extension":null,"sc-bytes":0,"cs(Referer)":null,"x-rs-certificate-observed-errors":"none","x-rs-certificate-hostname-threat-risk":"unavailable","c-ip":"192.168.1.1","x-rs-ocsp-error":null,"cs(Accept-Language)":null,"x-rs-certificate-hostname":"*.google.com","cs-categories":"Shopping;Software Downloads","s-supplier-name":"play.google.com","cs-auth-group":null,"cs-uri-port":443,"cs-bytes":0,"c-connect-type":"Transparent","x-cs-connection-negotiated-cipher-strength":"high","cs-method":"unknown","x-virus-id":null,"s-supplier-country":"None","cs-host":"play.google.com","x-rs-connection-negotiated-cipher-strength":"high","s-ip":"192.168.1.1","s-supplier-failures":null,"sc-status":0,"date":[2018,2,2],"x-bluecoat-application-name":"none","time-taken":1.0,"x-rs-certificate-hostname-category":"Search Engines/Portals","rs(Content-Type)":null,"time":[18,31,16],"x-exception-id":"tenant.content_filter_denied","s-supplier-ip":"192.168.1.1","x-cs-ocsp-error":null,"cs-threat-risk":"unavailable","sc-filter-result":"DENIED","cs-username":null},{"x-bluecoat-reference-id":"WA-LS-D_Standard-Deny2","x-cs-connection-negotiated-ssl-version":"TLSv1.2","cs-uri-extension":null,"cs-uri-scheme":"ssl","time":[18,31,16],"sc-filter-result":"DENIED","s-supplier-country":"None","cs-auth-group":null,"s-supplier-name":"play.google.com","cs-bytes":0,"c-ip":"192.168.1.1","date":[2018,2,2],"x-rs-certificate-hostname":"*.google.com","c-connect-type":"Transparent","x-bluecoat-application-operation":"none","s-supplier-ip":"192.168.1.1","s-ip":"192.168.1.1","cs(User-Agent)":null,"x-rs-certificate-hostname-category":"Search Engines/Portals","cs-categories":"Shopping;Software Downloads","cs-username":null,"s-action":"DENIED","x-rs-certificate-observed-errors":"none","cs(Accept-Language)":null,"time-taken":1.0,"x-cs-ocsp-error":null,"sc-bytes":0,"x-cs-connection-negotiated-cipher-strength":"high","cs-ip":"192.168.1.1","rs(Content-Type)":null,"x-virus-id":null,"cs-uri-port":443,"x-rs-connection-negotiated-cipher-strength":"high","sc-status":0,"cs-threat-risk":"unavailable","cs(Referer)":null,"cs-method":"unknown","x-rs-ocsp-error":null,"x-exception-id":"tenant.content_filter_denied","cs-host":"play.google.com","s-supplier-failures":null,"x-rs-certificate-hostname-threat-risk":"unavailable","x-bluecoat-application-name":"none"},{"x-bluecoat-application-operation":"none","x-virus-id":null,"c-connect-type":"Transparent","s-supplier-ip":"192.168.1.1","x-exception-id":"tenant.content_filter_denied","s-supplier-country":"None","cs-username":null,"x-rs-ocsp-error":null,"x-cs-connection-negotiated-ssl-version":"TLSv1.2","s-supplier-name":"play.google.com","cs-auth-group":null,"cs-uri-extension":null,"s-action":"DENIED","time-taken":1.0,"cs(User-Agent)":null,"c-ip":"192.168.1.1","s-ip":"192.168.1.1","cs-uri-scheme":"ssl","x-cs-ocsp-error":null,"cs-ip":"192.168.1.1","x-rs-certificate-hostname-threat-risk":"unavailable","x-rs-connection-negotiated-cipher-strength":"high","cs-uri-port":443,"cs-threat-risk":"unavailable","date":[2018,2,2],"rs(Content-Type)":null,"sc-status":0,"sc-filter-result":"DENIED","cs-bytes":0,"cs-host":"play.google.com","x-rs-certificate-hostname":"*.google.com","x-rs-certificate-hostname-category":"Search Engines/Portals","cs-method":"unknown","cs(Accept-Language)":null,"x-cs-connection-negotiated-cipher-strength":"high","x-bluecoat-application-name":"none","s-supplier-failures":null,"cs-categories":"Shopping;Software Downloads","cs(Referer)":null,"sc-bytes":0,"x-bluecoat-reference-id":"WA-LS-D_Standard-Deny2","time":[18,31,16],"x-rs-certificate-observed-errors":"none"},{"cs(User-Agent)":null,"cs-uri-port":443,"date":[2018,2,2],"cs-uri-scheme":"ssl","c-connect-type":"Transparent","x-rs-certificate-hostname":"*.google.com","x-virus-id":null,"time-taken":1.0,"cs-ip":"192.168.1.1","sc-filter-result":"DENIED","x-cs-ocsp-error":null,"x-exception-id":"tenant.content_filter_denied","sc-bytes":0,"x-bluecoat-reference-id":"WA-LS-D_Standard-Deny2","x-rs-certificate-hostname-threat-risk":"unavailable","x-bluecoat-application-operation":"none","c-ip":"192.168.1.1","s-supplier-name":"play.google.com","cs-username":null,"cs-threat-risk":"unavailable","cs(Referer)":null,"s-supplier-failures":null,"time":[18,31,16],"x-cs-connection-negotiated-cipher-strength":"high","rs(Content-Type)":null,"x-bluecoat-application-name":"none","cs-host":"play.google.com","cs-categories":"Shopping;Software Downloads","cs-auth-group":null,"cs-bytes":0,"sc-status":0,"s-supplier-country":"None","cs(Accept-Language)":null,"s-ip":"192.168.1.1","x-rs-certificate-hostname-category":"Search Engines/Portals","x-rs-ocsp-error":null,"x-rs-certificate-observed-errors":"none","s-action":"DENIED","cs-uri-extension":null,"x-cs-connection-negotiated-ssl-version":"TLSv1","cs-method":"unknown","s-supplier-ip":"192.168.1.1","x-rs-connection-negotiated-cipher-strength":"high"},{"x-rs-connection-negotiated-cipher-strength":"high","time":[18,31,16],"s-supplier-ip":"192.168.1.1","x-exception-id":"tenant.content_filter_denied","cs(Referer)":null,"cs-bytes":0,"cs-uri-scheme":"ssl","cs-auth-group":null,"x-bluecoat-reference-id":"WA-LS-D_Standard-Deny2","c-connect-type":"Transparent","cs(Accept-Language)":null,"cs-method":"unknown","s-supplier-name":"play.google.com","s-supplier-country":"None","cs(User-Agent)":null,"x-rs-certificate-observed-errors":"none","s-ip":"192.168.1.1","c-ip":"192.168.1.1","s-action":"DENIED","x-rs-ocsp-error":null,"x-bluecoat-application-operation":"none","rs(Content-Type)":null,"cs-uri-port":443,"x-rs-certificate-hostname-category":"Search Engines/Portals","x-cs-connection-negotiated-ssl-version":"TLSv1","sc-filter-result":"DENIED","cs-categories":"Shopping;Software Downloads","cs-username":null,"cs-ip":"192.168.1.1","time-taken":1.0,"cs-host":"play.google.com","s-supplier-failures":null,"x-bluecoat-application-name":"none","sc-status":0,"cs-threat-risk":"unavailable","date":[2018,2,2],"x-cs-connection-negotiated-cipher-strength":"high","x-virus-id":null,"x-rs-certificate-hostname":"*.google.com","cs-uri-extension":null,"x-cs-ocsp-error":null,"sc-bytes":0,"x-rs-certificate-hostname-threat-risk":"unavailable"},{"cs-uri-extension":null,"s-supplier-name":"play.google.com","x-virus-id":null,"s-supplier-country":"None","s-supplier-failures":null,"rs(Content-Type)":null,"x-exception-id":"tenant.content_filter_denied","c-ip":"192.168.1.1","cs(Accept-Language)":null,"x-rs-certificate-hostname":"*.google.com","x-bluecoat-application-name":"none","sc-status":0,"time":[18,31,16],"x-rs-certificate-hostname-category":"Search Engines/Portals","cs-username":null,"cs-uri-scheme":"ssl","cs-categories":"Shopping;Software Downloads","time-taken":1.0,"x-rs-ocsp-error":null,"x-rs-certificate-observed-errors":"none","cs-ip":"192.168.1.1","x-rs-certificate-hostname-threat-risk":"unavailable","x-cs-ocsp-error":null,"cs(User-Agent)":null,"cs-auth-group":null,"sc-filter-result":"DENIED","c-connect-type":"Transparent","cs-method":"unknown","s-action":"DENIED","date":[2018,2,2],"sc-bytes":0,"x-bluecoat-application-operation":"none","x-bluecoat-reference-id":"WA-LS-D_Standard-Deny2","x-cs-connection-negotiated-cipher-strength":"high","x-rs-connection-negotiated-cipher-strength":"high","s-ip":"192.168.1.1","cs-threat-risk":"unavailable","x-cs-connection-negotiated-ssl-version":"TLSv1.2","cs-bytes":0,"cs-host":"play.google.com","s-supplier-ip":"192.168.1.1","cs-uri-port":443,"cs(Referer)":null},{"cs(User-Agent)":null,"x-rs-connection-negotiated-cipher-strength":"high","cs(Accept-Language)":null,"x-cs-connection-negotiated-ssl-version":"TLSv1.2","sc-filter-result":"DENIED","x-exception-id":"tenant.content_filter_denied","cs-bytes":0,"s-supplier-ip":"192.168.1.1","c-connect-type":"Transparent","c-ip":"192.168.1.1","cs-categories":"Shopping;Software Downloads","x-virus-id":null,"cs-host":"play.google.com","x-bluecoat-reference-id":"WA-LS-D_Standard-Deny2","cs-ip":"192.168.1.1","s-supplier-name":"play.google.com","s-ip":"192.168.1.1","cs(Referer)":null,"time-taken":1.0,"x-rs-certificate-observed-errors":"none","cs-uri-port":443,"s-supplier-failures":null,"cs-username":null,"s-action":"DENIED","s-supplier-country":"None","x-rs-certificate-hostname":"*.google.com","x-bluecoat-application-name":"none","x-rs-ocsp-error":null,"x-rs-certificate-hostname-threat-risk":"unavailable","cs-auth-group":null,"x-cs-ocsp-error":null,"x-cs-connection-negotiated-cipher-strength":"high","x-bluecoat-application-operation":"none","cs-uri-scheme":"ssl","date":[2018,2,2],"x-rs-certificate-hostname-category":"Search Engines/Portals","cs-uri-extension":null,"sc-bytes":0,"sc-status":0,"cs-method":"unknown","time":[18,31,16],"cs-threat-risk":"unavailable","rs(Content-Type)":null},{"cs-username":null,"cs(Accept-Language)":null,"c-connect-type":"Transparent","x-virus-id":null,"cs(Referer)":null,"x-cs-ocsp-error":null,"cs(User-Agent)":null,"cs-categories":"Shopping;Software Downloads","s-ip":"192.168.1.1","c-ip":"192.168.1.1","x-exception-id":"tenant.content_filter_denied","cs-auth-group":null,"cs-ip":"192.168.1.1","x-rs-certificate-observed-errors":"none","sc-status":0,"sc-bytes":0,"cs-uri-port":443,"x-cs-connection-negotiated-ssl-version":"TLSv1.2","x-rs-certificate-hostname-threat-risk":"unavailable","cs-host":"play.google.com","cs-uri-extension":null,"cs-threat-risk":"unavailable","s-supplier-name":"play.google.com","x-rs-certificate-hostname-category":"Search Engines/Portals","cs-method":"unknown","cs-uri-scheme":"ssl","cs-bytes":0,"x-cs-connection-negotiated-cipher-strength":"high","s-supplier-country":"None","s-supplier-failures":null,"x-rs-certificate-hostname":"*.google.com","rs(Content-Type)":null,"sc-filter-result":"DENIED","x-rs-connection-negotiated-cipher-strength":"high","time":[18,31,16],"time-taken":1.0,"x-bluecoat-application-name":"none","x-bluecoat-reference-id":"WA-LS-D_Standard-Deny2","date":[2018,2,2],"x-bluecoat-application-operation":"none","x-rs-ocsp-error":null,"s-action":"DENIED","s-supplier-ip":"192.168.1.1"},{"x-exception-id":"tenant.content_filter_denied","cs-username":null,"date":[2018,2,2],"c-connect-type":"Transparent","x-bluecoat-application-operation":"none","rs(Content-Type)":null,"s-action":"DENIED","time-taken":1.0,"s-supplier-ip":"192.168.1.1","cs(User-Agent)":null,"x-cs-connection-negotiated-ssl-version":"TLSv1.2","x-rs-certificate-hostname-threat-risk":"unavailable","cs-ip":"192.168.1.1","cs-threat-risk":"unavailable","sc-filter-result":"DENIED","x-rs-connection-negotiated-cipher-strength":"high","cs-method":"unknown","x-rs-certificate-observed-errors":"none","s-ip":"192.168.1.1","cs-categories":"Shopping;Software Downloads","x-virus-id":null,"cs-auth-group":null,"cs(Referer)":null,"x-cs-ocsp-error":null,"cs-bytes":0,"x-bluecoat-reference-id":"WA-LS-D_Standard-Deny2","cs-uri-scheme":"ssl","cs-host":"play.google.com","x-rs-ocsp-error":null,"x-rs-certificate-hostname":"*.google.com","time":[18,31,18],"x-cs-connection-negotiated-cipher-strength":"high","s-supplier-name":"play.google.com","cs-uri-extension":null,"cs-uri-port":443,"cs(Accept-Language)":null,"x-bluecoat-application-name":"none","c-ip":"192.168.1.1","sc-status":0,"x-rs-certificate-hostname-category":"Search Engines/Portals","sc-bytes":0,"s-supplier-failures":null,"s-supplier-country":"None"},{"s-action":"DENIED","cs(Accept-Language)":null,"sc-bytes":0,"cs-bytes":0,"cs-host":"play.google.com","cs-method":"unknown","x-rs-ocsp-error":null,"x-virus-id":null,"cs-uri-extension":null,"cs-threat-risk":"unavailable","cs(User-Agent)":null,"x-rs-certificate-hostname":"*.google.com","cs(Referer)":null,"date":[2018,2,2],"x-rs-certificate-observed-errors":"none","x-cs-ocsp-error":null,"sc-status":0,"x-rs-certificate-hostname-category":"Search Engines/Portals","cs-auth-group":null,"cs-uri-scheme":"ssl","x-cs-connection-negotiated-cipher-strength":"high","x-bluecoat-application-name":"none","x-bluecoat-reference-id":"WA-LS-D_Standard-Deny2","x-cs-connection-negotiated-ssl-version":"TLSv1","time":[18,31,18],"c-connect-type":"Transparent","x-rs-connection-negotiated-cipher-strength":"high","s-ip":"192.168.1.1","s-supplier-name":"play.google.com","s-supplier-country":"None","cs-ip":"192.168.1.1","cs-categories":"Shopping;Software Downloads","time-taken":1.0,"c-ip":"192.168.1.1","x-rs-certificate-hostname-threat-risk":"unavailable","x-bluecoat-application-operation":"none","x-exception-id":"tenant.content_filter_denied","cs-username":null,"rs(Content-Type)":null,"s-supplier-failures":null,"cs-uri-port":443,"sc-filter-result":"DENIED","s-supplier-ip":"192.168.1.1"},{"s-ip":"192.168.1.1","cs-auth-group":null,"x-bluecoat-application-operation":"none","cs-categories":"Shopping;Software Downloads","time":[18,31,18],"cs-host":"play.google.com","x-exception-id":"tenant.content_filter_denied","date":[2018,2,2],"sc-bytes":0,"s-supplier-ip":"192.168.1.1","x-cs-ocsp-error":null,"x-rs-certificate-hostname-category":"Search Engines/Portals","s-action":"DENIED","cs-bytes":0,"cs(Accept-Language)":null,"cs-method":"unknown","cs-uri-scheme":"ssl","cs-username":null,"x-rs-connection-negotiated-cipher-strength":"high","x-bluecoat-reference-id":"WA-LS-D_Standard-Deny2","x-rs-certificate-observed-errors":"none","x-rs-certificate-hostname-threat-risk":"unavailable","time-taken":1.0,"x-bluecoat-application-name":"none","c-ip":"192.168.1.1","sc-filter-result":"DENIED","x-rs-ocsp-error":null,"s-supplier-country":"None","cs(Referer)":null,"x-cs-connection-negotiated-ssl-version":"TLSv1","x-cs-connection-negotiated-cipher-strength":"high","cs-uri-port":443,"x-rs-certificate-hostname":"*.google.com","sc-status":0,"cs-ip":"192.168.1.1","rs(Content-Type)":null,"cs(User-Agent)":null,"c-connect-type":"Transparent","cs-uri-extension":null,"s-supplier-failures":null,"s-supplier-name":"play.google.com","cs-threat-risk":"unavailable","x-virus-id":null},{"c-ip":"192.168.1.1","cs-auth-group":null,"x-cs-ocsp-error":null,"cs-uri-extension":null,"cs-threat-risk":"unavailable","x-cs-connection-negotiated-ssl-version":"TLSv1","time":[18,31,18],"s-supplier-failures":null,"x-virus-id":null,"cs-categories":"Business/Economy;Web Ads/Analytics","x-rs-certificate-hostname-threat-risk":"unavailable","x-bluecoat-reference-id":"WA-LS-D_Standard-Deny2","x-bluecoat-application-name":"none","sc-status":0,"s-supplier-name":"nqs-nl1-c2.example.com","s-ip":"192.168.1.1","x-rs-certificate-hostname-category":"Business/Economy","cs(User-Agent)":null,"cs-uri-scheme":"ssl","time-taken":1.0,"s-supplier-country":"None","x-rs-connection-negotiated-cipher-strength":"high","cs-username":null,"cs(Accept-Language)":null,"sc-bytes":0,"x-bluecoat-application-operation":"none","x-rs-certificate-observed-errors":"none","cs-bytes":0,"x-rs-certificate-hostname":"*.example.com","s-supplier-ip":"192.168.1.1","date":[2018,2,2],"rs(Content-Type)":null,"sc-filter-result":"DENIED","x-cs-connection-negotiated-cipher-strength":"high","c-connect-type":"Transparent","cs-method":"unknown","cs-uri-port":443,"cs(Referer)":null,"x-rs-ocsp-error":null,"x-exception-id":"tenant.content_filter_denied","cs-ip":"192.168.1.1","s-action":"DENIED","cs-host":"nqs-nl1-c2.example.com"},{"date":[2018,2,2],"sc-bytes":0,"x-bluecoat-application-name":"none","s-action":"DENIED","sc-filter-result":"DENIED","cs-bytes":0,"cs-threat-risk":"unavailable","time-taken":1.0,"sc-status":0,"x-rs-certificate-observed-errors":"none","cs(Accept-Language)":null,"cs-uri-port":443,"cs-host":"otf.msn.com","rs(Content-Type)":null,"cs(User-Agent)":null,"x-rs-certificate-hostname-category":"Search Engines/Portals","x-virus-id":null,"cs-categories":"Web Ads/Analytics","cs-auth-group":null,"c-connect-type":"Transparent","cs-uri-extension":null,"x-exception-id":"tenant.content_filter_denied","x-cs-connection-negotiated-cipher-strength":"high","cs(Referer)":null,"cs-ip":"192.168.1.1","x-rs-certificate-hostname":"udc.msn.com","cs-uri-scheme":"ssl","s-supplier-country":"None","x-cs-ocsp-error":null,"cs-method":"unknown","x-bluecoat-reference-id":"WA-LS-D_Standard-Deny2","x-rs-certificate-hostname-threat-risk":"unavailable","s-supplier-name":"otf.msn.com","s-supplier-failures":null,"x-cs-connection-negotiated-ssl-version":"TLSv1.2","time":[18,31,18],"cs-username":null,"x-rs-ocsp-error":null,"c-ip":"192.168.1.1","s-supplier-ip":"192.168.1.1","x-rs-connection-negotiated-cipher-strength":"high","s-ip":"192.168.1.1","x-bluecoat-application-operation":"none"},{"x-rs-connection-negotiated-cipher-strength":"high","time":[18,31,18],"x-rs-certificate-hostname-threat-risk":"unavailable","s-ip":"192.168.1.1","cs-categories":"Web Ads/Analytics","sc-filter-result":"DENIED","x-bluecoat-application-name":"none","x-cs-connection-negotiated-ssl-version":"TLSv1.2","cs-method":"unknown","cs-auth-group":null,"cs-uri-port":443,"s-supplier-ip":"192.168.1.1","cs-bytes":0,"s-supplier-name":"otf.msn.com","x-rs-ocsp-error":null,"cs-threat-risk":"unavailable","cs(Referer)":null,"c-ip":"192.168.1.1","x-rs-certificate-hostname":"udc.msn.com","date":[2018,2,2],"cs-username":null,"s-action":"DENIED","x-bluecoat-reference-id":"WA-LS-D_Standard-Deny2","cs(Accept-Language)":null,"x-rs-certificate-observed-errors":"none","cs-ip":"192.168.1.1","x-bluecoat-application-operation":"none","rs(Content-Type)":null,"x-rs-certificate-hostname-category":"Search Engines/Portals","cs(User-Agent)":null,"x-cs-connection-negotiated-cipher-strength":"high","s-supplier-failures":null,"x-cs-ocsp-error":null,"sc-bytes":0,"x-exception-id":"tenant.content_filter_denied","time-taken":1.0,"cs-uri-scheme":"ssl","cs-uri-extension":null,"sc-status":0,"c-connect-type":"Transparent","s-supplier-country":"None","x-virus-id":null,"cs-host":"otf.msn.com"},{"c-ip":"192.168.1.1","cs-bytes":0,"sc-status":0,"x-rs-certificate-hostname-category":"none","x-exception-id":"tenant.content_filter_denied","x-cs-connection-negotiated-cipher-strength":"high","cs(Referer)":null,"cs-uri-scheme":"ssl","s-supplier-name":"cont-5.p-cdn.us","time-taken":1.0,"cs-uri-port":443,"x-rs-ocsp-error":null,"x-rs-certificate-observed-errors":"none","s-supplier-failures":null,"cs-ip":"192.168.1.1","cs-threat-risk":"unavailable","cs(Accept-Language)":null,"c-connect-type":"Transparent","cs-host":"cont-5.p-cdn.us","sc-bytes":0,"x-rs-certificate-hostname":"*.p-cdn.us","x-rs-certificate-hostname-threat-risk":"unavailable","cs-method":"unknown","rs(Content-Type)":null,"cs-auth-group":null,"sc-filter-result":"DENIED","cs-username":null,"x-bluecoat-application-operation":"none","s-action":"DENIED","date":[2018,2,2],"cs(User-Agent)":null,"x-rs-connection-negotiated-cipher-strength":"high","x-cs-ocsp-error":null,"x-bluecoat-application-name":"none","s-supplier-country":"None","s-ip":"192.168.1.1","x-virus-id":null,"x-cs-connection-negotiated-ssl-version":"TLSv1","s-supplier-ip":"192.168.1.1","cs-uri-extension":null,"x-bluecoat-reference-id":"WA-SP-D_Cat-None","cs-categories":"none","time":[18,31,18]},{"x-bluecoat-application-operation":"none","cs-threat-risk":"unavailable","time":[18,31,18],"cs-auth-group":null,"cs-bytes":0,"sc-bytes":0,"cs(Accept-Language)":null,"x-cs-ocsp-error":null,"x-rs-certificate-hostname-category":"none","c-ip":"192.168.1.1","cs-uri-port":443,"x-bluecoat-reference-id":"WA-SP-D_Cat-None","cs-uri-extension":null,"s-supplier-failures":null,"time-taken":1.0,"s-action":"DENIED","date":[2018,2,2],"rs(Content-Type)":null,"cs-method":"unknown","s-ip":"192.168.1.1","cs-host":"cont-5.p-cdn.us","x-rs-connection-negotiated-cipher-strength":"high","cs-uri-scheme":"ssl","cs(User-Agent)":null,"sc-status":0,"x-rs-ocsp-error":null,"cs-categories":"none","x-cs-connection-negotiated-cipher-strength":"high","cs-ip":"192.168.1.1","x-exception-id":"tenant.content_filter_denied","x-rs-certificate-hostname":"*.p-cdn.us","s-supplier-country":"None","x-rs-certificate-hostname-threat-risk":"unavailable","cs(Referer)":null,"sc-filter-result":"DENIED","c-connect-type":"Transparent","x-virus-id":null,"s-supplier-ip":"192.168.1.1","s-supplier-name":"cont-5.p-cdn.us","x-cs-connection-negotiated-ssl-version":"TLSv1","x-bluecoat-application-name":"none","x-rs-certificate-observed-errors":"none","cs-username":null},{"c-ip":"192.168.1.1","cs-threat-risk":"unavailable","x-virus-id":null,"cs-host":"nqs-nl1-c2.example.com","sc-bytes":0,"x-rs-certificate-hostname-threat-risk":"unavailable","x-rs-connection-negotiated-cipher-strength":"high","x-bluecoat-application-operation":"none","s-supplier-name":"nqs-nl1-c2.example.com","cs-ip":"192.168.1.1","cs(User-Agent)":null,"s-supplier-ip":"192.168.1.1","x-cs-ocsp-error":null,"cs-uri-extension":null,"date":[2018,2,2],"x-rs-certificate-hostname-category":"Business/Economy","x-bluecoat-application-name":"none","cs-username":null,"time":[18,31,18],"x-bluecoat-reference-id":"WA-LS-D_Standard-Deny2","sc-filter-result":"DENIED","s-action":"DENIED","cs-method":"unknown","x-exception-id":"tenant.content_filter_denied","cs-uri-scheme":"ssl","x-cs-connection-negotiated-ssl-version":"TLSv1.2","x-rs-ocsp-error":null,"rs(Content-Type)":null,"cs-uri-port":443,"s-supplier-failures":null,"c-connect-type":"Transparent","x-rs-certificate-observed-errors":"none","cs-auth-group":null,"s-supplier-country":"None","cs-bytes":0,"time-taken":1.0,"x-rs-certificate-hostname":"*.example.com","s-ip":"192.168.1.1","cs(Accept-Language)":null,"cs(Referer)":null,"sc-status":0,"cs-categories":"Business/Economy;Web Ads/Analytics","x-cs-connection-negotiated-cipher-strength":"high"},{"time":[18,31,18],"x-bluecoat-application-name":"none","cs-auth-group":null,"x-rs-certificate-hostname":"*.fwmrm.net","s-action":"DENIED","x-exception-id":"tenant.content_filter_denied","cs(Referer)":null,"x-rs-connection-negotiated-cipher-strength":"high","cs(User-Agent)":null,"cs-ip":"192.168.1.1","x-cs-connection-negotiated-ssl-version":"TLSv1","x-virus-id":null,"x-cs-connection-negotiated-cipher-strength":"high","sc-filter-result":"DENIED","date":[2018,2,2],"x-rs-certificate-observed-errors":"none","time-taken":1.0,"rs(Content-Type)":null,"s-supplier-name":"mssl.fwmrm.net","cs-bytes":0,"cs-uri-port":443,"x-rs-certificate-hostname-category":"Web Ads/Analytics","cs-username":null,"sc-status":0,"cs-method":"unknown","x-cs-ocsp-error":null,"cs-uri-scheme":"ssl","x-rs-ocsp-error":null,"x-bluecoat-reference-id":"WA-LS-D_Standard-Deny2","s-supplier-failures":null,"s-supplier-ip":"192.168.1.1","c-connect-type":"Transparent","cs-uri-extension":null,"s-supplier-country":"None","x-rs-certificate-hostname-threat-risk":"unavailable","sc-bytes":0,"cs-host":"mssl.fwmrm.net","c-ip":"192.168.1.1","s-ip":"192.168.1.1","x-bluecoat-application-operation":"none","cs-threat-risk":"unavailable","cs-categories":"Streaming_Video_Required_Analytics;Web Ads/Analytics","cs(Accept-Language)":null},{"x-rs-certificate-hostname":"*.fwmrm.net","cs-method":"unknown","time-taken":1.0,"cs-auth-group":null,"x-cs-connection-negotiated-cipher-strength":"high","cs-uri-port":443,"s-supplier-failures":null,"x-virus-id":null,"s-supplier-ip":"192.168.1.1","x-bluecoat-application-name":"none","cs(User-Agent)":null,"cs-username":null,"cs-host":"mssl.fwmrm.net","c-connect-type":"Transparent","rs(Content-Type)":null,"cs-ip":"192.168.1.1","x-rs-ocsp-error":null,"x-cs-ocsp-error":null,"cs-uri-extension":null,"x-cs-connection-negotiated-ssl-version":"TLSv1","cs(Referer)":null,"c-ip":"192.168.1.1","s-ip":"192.168.1.1","s-supplier-country":"None","cs-bytes":0,"x-rs-connection-negotiated-cipher-strength":"high","x-rs-certificate-hostname-threat-risk":"unavailable","x-bluecoat-reference-id":"WA-LS-D_Standard-Deny2","sc-status":0,"time":[18,31,18],"sc-bytes":0,"x-rs-certificate-observed-errors":"none","s-action":"DENIED","date":[2018,2,2],"x-exception-id":"tenant.content_filter_denied","x-bluecoat-application-operation":"none","cs-uri-scheme":"ssl","x-rs-certificate-hostname-category":"Web Ads/Analytics","s-supplier-name":"mssl.fwmrm.net","cs(Accept-Language)":null,"cs-threat-risk":"unavailable","sc-filter-result":"DENIED","cs-categories":"Streaming_Video_Required_Analytics;Web Ads/Analytics"},{"x-bluecoat-application-name":"none","c-connect-type":"Transparent","cs-uri-scheme":"ssl","sc-filter-result":"DENIED","sc-bytes":0,"s-supplier-ip":"192.168.1.1","x-exception-id":"tenant.content_filter_denied","time-taken":1.0,"x-cs-connection-negotiated-cipher-strength":"high","s-action":"DENIED","x-rs-certificate-hostname":"*.google.com","x-rs-connection-negotiated-cipher-strength":"high","c-ip":"192.168.1.1","rs(Content-Type)":null,"cs-auth-group":null,"cs-bytes":0,"cs(Accept-Language)":null,"x-rs-certificate-observed-errors":"none","cs-ip":"192.168.1.1","s-supplier-name":"play.google.com","x-bluecoat-reference-id":"WA-LS-D_Standard-Deny2","s-supplier-country":"None","cs(User-Agent)":null,"cs-categories":"Shopping;Software Downloads","x-cs-connection-negotiated-ssl-version":"TLSv1.2","cs(Referer)":null,"x-rs-ocsp-error":null,"cs-username":null,"time":[18,31,18],"x-cs-ocsp-error":null,"date":[2018,2,2],"x-bluecoat-application-operation":"none","s-supplier-failures":null,"x-virus-id":null,"cs-method":"unknown","cs-uri-extension":null,"sc-status":0,"cs-threat-risk":"unavailable","x-rs-certificate-hostname-threat-risk":"unavailable","cs-uri-port":443,"x-rs-certificate-hostname-category":"Search Engines/Portals","s-ip":"192.168.1.1","cs-host":"play.google.com"},{"s-supplier-failures":null,"x-rs-certificate-hostname":"*.google.com","cs-threat-risk":"unavailable","x-rs-certificate-hostname-threat-risk":"unavailable","x-bluecoat-application-operation":"none","sc-filter-result":"DENIED","x-rs-ocsp-error":null,"x-virus-id":null,"time-taken":1.0,"s-ip":"192.168.1.1","cs(Referer)":null,"cs-uri-port":443,"x-cs-connection-negotiated-ssl-version":"TLSv1.2","date":[2018,2,2],"cs-uri-scheme":"ssl","c-ip":"192.168.1.1","cs-method":"unknown","sc-bytes":0,"cs-ip":"192.168.1.1","x-bluecoat-application-name":"none","s-action":"DENIED","s-supplier-name":"play.google.com","c-connect-type":"Transparent","cs-username":null,"time":[18,31,18],"cs-bytes":0,"x-cs-connection-negotiated-cipher-strength":"high","cs-uri-extension":null,"cs(Accept-Language)":null,"x-rs-certificate-hostname-category":"Search Engines/Portals","x-cs-ocsp-error":null,"rs(Content-Type)":null,"cs-host":"play.google.com","cs(User-Agent)":null,"cs-auth-group":null,"sc-status":0,"x-bluecoat-reference-id":"WA-LS-D_Standard-Deny2","cs-categories":"Shopping;Software Downloads","x-exception-id":"tenant.content_filter_denied","s-supplier-country":"None","x-rs-connection-negotiated-cipher-strength":"high","s-supplier-ip":"192.168.1.1","x-rs-certificate-observed-errors":"none"},{"cs(Accept-Language)":null,"cs-auth-group":null,"sc-filter-result":"DENIED","x-rs-connection-negotiated-cipher-strength":"high","cs-uri-extension":null,"cs-username":null,"x-rs-ocsp-error":null,"cs(Referer)":null,"s-action":"DENIED","x-bluecoat-application-operation":"none","x-bluecoat-reference-id":"WA-LS-D_Standard-Deny2","x-rs-certificate-hostname":"*.google.com","rs(Content-Type)":null,"x-rs-certificate-observed-errors":"none","x-exception-id":"tenant.content_filter_denied","x-cs-connection-negotiated-ssl-version":"TLSv1.2","s-supplier-failures":null,"cs-threat-risk":"unavailable","sc-bytes":0,"x-bluecoat-application-name":"none","cs-bytes":0,"cs-host":"play.google.com","cs-uri-scheme":"ssl","cs-method":"unknown","cs-ip":"192.168.1.1","cs-uri-port":443,"c-connect-type":"Transparent","time":[18,31,18],"c-ip":"192.168.1.1","cs(User-Agent)":null,"time-taken":1.0,"s-supplier-country":"None","x-rs-certificate-hostname-category":"Search Engines/Portals","x-cs-connection-negotiated-cipher-strength":"high","x-cs-ocsp-error":null,"x-virus-id":null,"s-supplier-ip":"192.168.1.1","sc-status":0,"date":[2018,2,2],"s-supplier-name":"play.google.com","s-ip":"192.168.1.1","cs-categories":"Shopping;Software Downloads","x-rs-certificate-hostname-threat-risk":"unavailable"},{"cs(Accept-Language)":null,"x-exception-id":"tenant.content_filter_denied","x-cs-connection-negotiated-cipher-strength":"high","x-cs-connection-negotiated-ssl-version":"TLSv1.2","cs-method":"unknown","cs-bytes":0,"x-rs-certificate-observed-errors":"none","s-ip":"192.168.1.1","x-rs-ocsp-error":null,"x-bluecoat-application-operation":"none","cs-threat-risk":"unavailable","cs(Referer)":null,"sc-status":0,"x-rs-certificate-hostname":"*.hb.omtrdc.net","cs-ip":"192.168.1.1","cs-categories":"Streaming_Video_Required_Analytics;Web Ads/Analytics","x-virus-id":null,"cs-uri-extension":null,"cs-auth-group":null,"cs-uri-scheme":"ssl","s-supplier-name":"cbsinteractive.hb.omtrdc.net","s-supplier-failures":null,"c-ip":"192.168.1.1","rs(Content-Type)":null,"x-cs-ocsp-error":null,"cs(User-Agent)":null,"s-action":"DENIED","cs-uri-port":443,"x-rs-connection-negotiated-cipher-strength":"high","s-supplier-ip":"192.168.1.1","c-connect-type":"Transparent","sc-bytes":0,"date":[2018,2,2],"cs-host":"cbsinteractive.hb.omtrdc.net","time-taken":1.0,"cs-username":null,"x-bluecoat-reference-id":"WA-LS-D_Standard-Deny2","time":[18,31,18],"x-bluecoat-application-name":"none","x-rs-certificate-hostname-category":"Web Ads/Analytics","sc-filter-result":"DENIED","x-rs-certificate-hostname-threat-risk":"unavailable","s-supplier-country":"None"},{"s-ip":"192.168.1.1","time-taken":1.0,"s-supplier-country":"None","cs-uri-extension":null,"cs-bytes":0,"x-rs-certificate-hostname-threat-risk":"unavailable","x-bluecoat-application-name":"none","x-exception-id":"tenant.content_filter_denied","cs-categories":"Web Ads/Analytics","c-connect-type":"Transparent","x-rs-certificate-hostname":"*.spots.im","x-cs-connection-negotiated-cipher-strength":"high","sc-filter-result":"DENIED","c-ip":"192.168.1.1","x-rs-certificate-hostname-category":"Placeholders","cs-host":"cent.spots.im","x-bluecoat-reference-id":"WA-LS-D_Standard-Deny2","x-cs-ocsp-error":null,"cs-uri-scheme":"ssl","x-virus-id":null,"time":[18,31,18],"cs-threat-risk":"unavailable","cs-ip":"192.168.1.1","cs-auth-group":null,"s-supplier-name":"cent.spots.im","cs(User-Agent)":null,"date":[2018,2,2],"s-supplier-failures":null,"rs(Content-Type)":null,"x-bluecoat-application-operation":"none","sc-status":0,"cs(Referer)":null,"cs(Accept-Language)":null,"s-supplier-ip":"192.168.1.1","x-rs-connection-negotiated-cipher-strength":"high","x-rs-ocsp-error":null,"cs-method":"unknown","x-rs-certificate-observed-errors":"none","x-cs-connection-negotiated-ssl-version":"TLSv1.2","cs-username":null,"s-action":"DENIED","sc-bytes":0,"cs-uri-port":443},{"cs-host":"cbsinteractive.hb.omtrdc.net","cs-uri-scheme":"ssl","cs(Referer)":null,"x-rs-ocsp-error":null,"x-rs-certificate-hostname-category":"Web Ads/Analytics","x-rs-certificate-hostname":"*.hb.omtrdc.net","cs-bytes":0,"x-cs-connection-negotiated-ssl-version":"TLSv1.2","c-connect-type":"Transparent","c-ip":"192.168.1.1","x-rs-certificate-observed-errors":"none","cs-uri-extension":null,"cs-method":"unknown","cs-categories":"Streaming_Video_Required_Analytics;Web Ads/Analytics","s-supplier-ip":"192.168.1.1","time":[18,31,18],"time-taken":1.0,"cs(User-Agent)":null,"x-exception-id":"tenant.content_filter_denied","x-cs-connection-negotiated-cipher-strength":"high","date":[2018,2,2],"x-bluecoat-application-operation":"none","x-rs-connection-negotiated-cipher-strength":"high","s-supplier-name":"cbsinteractive.hb.omtrdc.net","x-rs-certificate-hostname-threat-risk":"unavailable","cs-uri-port":443,"cs-ip":"192.168.1.1","rs(Content-Type)":null,"x-cs-ocsp-error":null,"cs(Accept-Language)":null,"sc-status":0,"x-bluecoat-application-name":"none","sc-bytes":0,"cs-threat-risk":"unavailable","s-ip":"192.168.1.1","s-supplier-country":"None","sc-filter-result":"DENIED","x-virus-id":null,"cs-username":null,"cs-auth-group":null,"x-bluecoat-reference-id":"WA-LS-D_Standard-Deny2","s-supplier-failures":null,"s-action":"DENIED"},{"x-cs-connection-negotiated-cipher-strength":"high","cs-host":"otf.msn.com","sc-bytes":0,"s-supplier-ip":"192.168.1.1","x-cs-ocsp-error":null,"cs-auth-group":null,"s-supplier-name":"otf.msn.com","cs-uri-scheme":"ssl","cs-ip":"192.168.1.1","c-connect-type":"Transparent","c-ip":"192.168.1.1","x-rs-certificate-hostname-category":"Search Engines/Portals","x-virus-id":null,"cs-threat-risk":"unavailable","time":[18,31,18],"rs(Content-Type)":null,"x-bluecoat-application-operation":"none","sc-status":0,"cs-username":null,"x-rs-ocsp-error":null,"sc-filter-result":"DENIED","x-rs-certificate-observed-errors":"none","cs-categories":"Web Ads/Analytics","x-cs-connection-negotiated-ssl-version":"TLSv1.2","x-bluecoat-reference-id":"WA-LS-D_Standard-Deny2","s-supplier-country":"None","cs-uri-port":443,"cs-bytes":0,"x-exception-id":"tenant.content_filter_denied","cs(Accept-Language)":null,"x-rs-certificate-hostname-threat-risk":"unavailable","cs-method":"unknown","cs-uri-extension":null,"s-action":"DENIED","x-bluecoat-application-name":"none","x-rs-connection-negotiated-cipher-strength":"high","s-ip":"192.168.1.1","cs(User-Agent)":null,"x-rs-certificate-hostname":"udc.msn.com","s-supplier-failures":null,"date":[2018,2,2],"cs(Referer)":null,"time-taken":1.0},{"x-cs-connection-negotiated-ssl-version":"TLSv1.2","x-bluecoat-application-operation":"none","cs-host":"play.google.com","x-exception-id":"tenant.content_filter_denied","s-ip":"192.168.1.1","x-virus-id":null,"cs-method":"unknown","x-bluecoat-application-name":"none","sc-status":0,"x-rs-certificate-hostname":"*.google.com","date":[2018,2,2],"x-cs-connection-negotiated-cipher-strength":"high","s-supplier-name":"play.google.com","cs-auth-group":null,"cs-categories":"Shopping;Software Downloads","cs-threat-risk":"unavailable","x-rs-certificate-hostname-threat-risk":"unavailable","cs(Accept-Language)":null,"sc-bytes":0,"x-rs-certificate-observed-errors":"none","cs(Referer)":null,"cs-bytes":0,"s-supplier-ip":"192.168.1.1","s-action":"DENIED","rs(Content-Type)":null,"s-supplier-failures":null,"x-bluecoat-reference-id":"WA-LS-D_Standard-Deny2","c-connect-type":"Transparent","sc-filter-result":"DENIED","s-supplier-country":"None","time-taken":1.0,"c-ip":"192.168.1.1","cs(User-Agent)":null,"x-rs-certificate-hostname-category":"Search Engines/Portals","cs-uri-extension":null,"cs-username":null,"cs-uri-port":443,"x-rs-connection-negotiated-cipher-strength":"high","x-cs-ocsp-error":null,"cs-uri-scheme":"ssl","x-rs-ocsp-error":null,"time":[18,31,18],"cs-ip":"192.168.1.1"},{"cs-uri-extension":null,"cs-ip":"192.168.1.1","date":[2018,2,2],"x-rs-certificate-hostname-threat-risk":"unavailable","time":[18,31,18],"cs-bytes":0,"s-supplier-name":"play.google.com","cs(Accept-Language)":null,"s-supplier-failures":null,"x-rs-certificate-hostname":"*.google.com","x-bluecoat-application-name":"none","c-connect-type":"Transparent","x-bluecoat-reference-id":"WA-LS-D_Standard-Deny2","x-bluecoat-application-operation":"none","cs-threat-risk":"unavailable","x-rs-connection-negotiated-cipher-strength":"high","cs-categories":"Shopping;Software Downloads","s-ip":"192.168.1.1","rs(Content-Type)":null,"sc-bytes":0,"cs-uri-scheme":"ssl","cs(User-Agent)":null,"c-ip":"192.168.1.1","x-cs-connection-negotiated-cipher-strength":"high","s-supplier-ip":"192.168.1.1","cs-uri-port":443,"s-action":"DENIED","cs-username":null,"sc-status":0,"x-rs-ocsp-error":null,"x-cs-ocsp-error":null,"cs-host":"play.google.com","cs-auth-group":null,"x-exception-id":"tenant.content_filter_denied","x-rs-certificate-observed-errors":"none","x-cs-connection-negotiated-ssl-version":"TLSv1.2","time-taken":1.0,"x-rs-certificate-hostname-category":"Search Engines/Portals","s-supplier-country":"None","cs-method":"unknown","cs(Referer)":null,"sc-filter-result":"DENIED","x-virus-id":null},{"x-rs-certificate-observed-errors":"none","s-supplier-name":"play.google.com","x-cs-ocsp-error":null,"x-virus-id":null,"cs(Accept-Language)":null,"cs-uri-scheme":"ssl","x-bluecoat-reference-id":"WA-LS-D_Standard-Deny2","c-ip":"192.168.1.1","x-cs-connection-negotiated-cipher-strength":"high","cs-host":"play.google.com","cs(Referer)":null,"x-bluecoat-application-name":"none","sc-bytes":0,"time-taken":1.0,"time":[18,31,18],"cs(User-Agent)":null,"x-rs-certificate-hostname-category":"Search Engines/Portals","rs(Content-Type)":null,"x-cs-connection-negotiated-ssl-version":"TLSv1.2","s-action":"DENIED","x-bluecoat-application-operation":"none","x-rs-ocsp-error":null,"cs-uri-extension":null,"x-exception-id":"tenant.content_filter_denied","s-supplier-failures":null,"s-supplier-country":"None","sc-filter-result":"DENIED","cs-uri-port":443,"sc-status":0,"x-rs-connection-negotiated-cipher-strength":"high","s-ip":"192.168.1.1","x-rs-certificate-hostname":"*.google.com","cs-categories":"Shopping;Software Downloads","date":[2018,2,2],"cs-username":null,"cs-method":"unknown","cs-bytes":0,"cs-ip":"192.168.1.1","cs-auth-group":null,"c-connect-type":"Transparent","cs-threat-risk":"unavailable","x-rs-certificate-hostname-threat-risk":"unavailable","s-supplier-ip":"192.168.1.1"},{"x-rs-connection-negotiated-cipher-strength":"high","cs(User-Agent)":null,"cs-bytes":0,"s-action":"DENIED","s-ip":"192.168.1.1","c-connect-type":"Transparent","cs-uri-scheme":"ssl","x-rs-certificate-hostname":"*.google.com","s-supplier-failures":null,"cs-host":"play.google.com","s-supplier-ip":"192.168.1.1","cs(Accept-Language)":null,"cs-ip":"192.168.1.1","time-taken":1.0,"sc-status":0,"x-rs-certificate-hostname-category":"Search Engines/Portals","x-bluecoat-application-operation":"none","cs-uri-extension":null,"cs-username":null,"x-rs-certificate-observed-errors":"none","x-cs-ocsp-error":null,"s-supplier-country":"None","cs-threat-risk":"unavailable","date":[2018,2,2],"cs(Referer)":null,"cs-categories":"Shopping;Software Downloads","sc-filter-result":"DENIED","cs-method":"unknown","c-ip":"192.168.1.1","cs-auth-group":null,"time":[18,31,18],"x-rs-certificate-hostname-threat-risk":"unavailable","rs(Content-Type)":null,"x-rs-ocsp-error":null,"x-cs-connection-negotiated-ssl-version":"TLSv1.2","x-exception-id":"tenant.content_filter_denied","cs-uri-port":443,"x-virus-id":null,"x-cs-connection-negotiated-cipher-strength":"high","x-bluecoat-application-name":"none","x-bluecoat-reference-id":"WA-LS-D_Standard-Deny2","sc-bytes":0,"s-supplier-name":"play.google.com"},{"cs-method":"unknown","cs-ip":"192.168.1.1","cs(Accept-Language)":null,"cs-uri-port":443,"c-connect-type":"Transparent","s-supplier-name":"play.google.com","cs-username":null,"date":[2018,2,2],"cs-bytes":0,"cs(Referer)":null,"x-bluecoat-reference-id":"WA-LS-D_Standard-Deny2","sc-status":0,"x-virus-id":null,"cs(User-Agent)":null,"time-taken":1.0,"s-ip":"192.168.1.1","cs-auth-group":null,"time":[18,31,18],"cs-host":"play.google.com","x-bluecoat-application-name":"none","sc-filter-result":"DENIED","s-supplier-ip":"192.168.1.1","x-rs-certificate-observed-errors":"none","x-exception-id":"tenant.content_filter_denied","cs-uri-scheme":"ssl","sc-bytes":0,"cs-categories":"Shopping;Software Downloads","c-ip":"192.168.1.1","x-rs-connection-negotiated-cipher-strength":"high","x-cs-connection-negotiated-ssl-version":"TLSv1.2","rs(Content-Type)":null,"x-rs-ocsp-error":null,"cs-threat-risk":"unavailable","s-supplier-country":"None","x-rs-certificate-hostname-category":"Search Engines/Portals","x-cs-connection-negotiated-cipher-strength":"high","cs-uri-extension":null,"x-bluecoat-application-operation":"none","s-supplier-failures":null,"x-cs-ocsp-error":null,"s-action":"DENIED","x-rs-certificate-hostname":"*.google.com","x-rs-certificate-hostname-threat-risk":"unavailable"},{"x-bluecoat-application-name":"none","sc-status":0,"sc-filter-result":"DENIED","x-bluecoat-application-operation":"none","c-ip":"192.168.1.1","s-supplier-country":"None","x-rs-ocsp-error":null,"x-exception-id":"tenant.content_filter_denied","cs-categories":"Shopping;Software Downloads","x-cs-ocsp-error":null,"x-bluecoat-reference-id":"WA-LS-D_Standard-Deny2","x-cs-connection-negotiated-cipher-strength":"high","cs-uri-port":443,"x-rs-certificate-hostname-threat-risk":"unavailable","s-supplier-ip":"192.168.1.1","cs-method":"unknown","sc-bytes":0,"cs-ip":"192.168.1.1","time":[18,31,18],"x-virus-id":null,"cs-uri-scheme":"ssl","rs(Content-Type)":null,"date":[2018,2,2],"x-cs-connection-negotiated-ssl-version":"TLSv1","cs(User-Agent)":null,"x-rs-certificate-hostname-category":"Search Engines/Portals","cs-uri-extension":null,"cs-host":"play.google.com","time-taken":1.0,"cs(Accept-Language)":null,"cs-threat-risk":"unavailable","s-supplier-failures":null,"cs-bytes":0,"c-connect-type":"Transparent","cs(Referer)":null,"x-rs-connection-negotiated-cipher-strength":"high","x-rs-certificate-hostname":"*.google.com","cs-auth-group":null,"s-supplier-name":"play.google.com","s-action":"DENIED","s-ip":"192.168.1.1","x-rs-certificate-observed-errors":"none","cs-username":null},{"time-taken":1.0,"cs-uri-scheme":"ssl","x-cs-connection-negotiated-cipher-strength":"high","cs-host":"play.google.com","cs-categories":"Shopping;Software Downloads","sc-status":0,"cs-threat-risk":"unavailable","c-ip":"192.168.1.1","time":[18,31,18],"cs-bytes":0,"cs-auth-group":null,"x-exception-id":"tenant.content_filter_denied","s-supplier-failures":null,"cs-method":"unknown","x-cs-connection-negotiated-ssl-version":"TLSv1","sc-filter-result":"DENIED","rs(Content-Type)":null,"x-bluecoat-reference-id":"WA-LS-D_Standard-Deny2","cs-ip":"192.168.1.1","cs(User-Agent)":null,"x-bluecoat-application-name":"none","x-rs-ocsp-error":null,"x-rs-certificate-hostname-category":"Search Engines/Portals","x-cs-ocsp-error":null,"x-bluecoat-application-operation":"none","x-virus-id":null,"cs(Referer)":null,"x-rs-certificate-observed-errors":"none","s-ip":"192.168.1.1","cs-uri-extension":null,"cs-username":null,"c-connect-type":"Transparent","x-rs-connection-negotiated-cipher-strength":"high","date":[2018,2,2],"s-supplier-name":"play.google.com","sc-bytes":0,"cs-uri-port":443,"s-supplier-country":"None","x-rs-certificate-hostname":"*.google.com","s-supplier-ip":"192.168.1.1","cs(Accept-Language)":null,"x-rs-certificate-hostname-threat-risk":"unavailable","s-action":"DENIED"},{"x-cs-connection-negotiated-ssl-version":"TLSv1.2","x-bluecoat-application-operation":"none","x-rs-connection-negotiated-cipher-strength":"high","time":[18,31,18],"s-supplier-country":"None","time-taken":196.0,"x-cs-ocsp-error":null,"x-rs-ocsp-error":null,"s-supplier-name":"client.wns.windows.com","sc-bytes":332,"x-virus-id":null,"rs(Content-Type)":null,"x-rs-certificate-hostname":"*.wns.windows.com","c-ip":"192.168.1.1","cs(Accept-Language)":null,"cs-auth-group":null,"c-connect-type":"Transparent","sc-filter-result":"OBSERVED","x-bluecoat-reference-id":"WA-SP-A_Standard-Allow","x-rs-certificate-hostname-category":"Technology/Internet","cs-username":null,"date":[2018,2,2],"x-bluecoat-application-name":"none","s-ip":"192.168.1.1","cs-threat-risk":"unavailable","cs-categories":"Technology/Internet","x-exception-id":null,"x-cs-connection-negotiated-cipher-strength":"high","cs-ip":"192.168.1.1","s-supplier-failures":null,"x-rs-certificate-observed-errors":"none","cs-uri-extension":null,"s-action":"TUNNELED","cs-host":"client.wns.windows.com","cs(User-Agent)":null,"s-supplier-ip":"192.168.1.1","cs-uri-port":443,"x-rs-certificate-hostname-threat-risk":"unavailable","sc-status":0,"cs(Referer)":null,"cs-uri-scheme":"ssl","cs-bytes":1692,"cs-method":"unknown"},{"s-action":"DENIED","x-cs-ocsp-error":null,"s-supplier-ip":"192.168.1.1","date":[2018,2,2],"x-rs-certificate-hostname-threat-risk":"unavailable","cs-bytes":0,"cs-uri-scheme":"ssl","cs(Accept-Language)":null,"x-rs-certificate-observed-errors":"none","s-supplier-failures":null,"x-cs-connection-negotiated-ssl-version":"TLSv1","cs-host":"otf.msn.com","c-ip":"192.168.1.1","s-supplier-name":"otf.msn.com","x-virus-id":null,"s-supplier-country":"None","sc-status":0,"cs-categories":"Web Ads/Analytics","cs-auth-group":null,"sc-bytes":0,"time-taken":1.0,"cs(Referer)":null,"s-ip":"192.168.1.1","cs-ip":"192.168.1.1","cs-uri-port":443,"x-rs-certificate-hostname":"udc.msn.com","x-exception-id":"tenant.content_filter_denied","cs(User-Agent)":null,"x-rs-certificate-hostname-category":"Search Engines/Portals","x-bluecoat-application-operation":"none","rs(Content-Type)":null,"c-connect-type":"Transparent","x-rs-ocsp-error":null,"x-bluecoat-reference-id":"WA-LS-D_Standard-Deny2","cs-username":null,"cs-threat-risk":"unavailable","time":[18,31,18],"x-rs-connection-negotiated-cipher-strength":"high","cs-method":"unknown","cs-uri-extension":null,"x-bluecoat-application-name":"none","x-cs-connection-negotiated-cipher-strength":"high","sc-filter-result":"DENIED"},{"cs(User-Agent)":null,"cs(Referer)":null,"cs-auth-group":null,"cs(Accept-Language)":null,"s-supplier-name":"play.google.com","x-cs-connection-negotiated-ssl-version":"TLSv1.2","cs-uri-port":443,"c-connect-type":"Transparent","x-rs-certificate-hostname":"*.google.com","s-action":"DENIED","x-rs-certificate-hostname-threat-risk":"unavailable","sc-bytes":0,"cs-ip":"192.168.1.1","sc-filter-result":"DENIED","x-bluecoat-application-name":"none","cs-uri-scheme":"ssl","cs-threat-risk":"unavailable","x-rs-certificate-observed-errors":"none","time-taken":1.0,"x-virus-id":null,"cs-host":"play.google.com","x-bluecoat-application-operation":"none","cs-username":null,"sc-status":0,"s-supplier-failures":null,"x-rs-certificate-hostname-category":"Search Engines/Portals","rs(Content-Type)":null,"c-ip":"192.168.1.1","x-rs-connection-negotiated-cipher-strength":"high","cs-bytes":0,"x-cs-connection-negotiated-cipher-strength":"high","time":[18,31,18],"date":[2018,2,2],"s-supplier-country":"None","s-ip":"192.168.1.1","cs-uri-extension":null,"x-exception-id":"tenant.content_filter_denied","cs-method":"unknown","x-cs-ocsp-error":null,"x-bluecoat-reference-id":"WA-LS-D_Standard-Deny2","x-rs-ocsp-error":null,"s-supplier-ip":"192.168.1.1","cs-categories":"Shopping;Software Downloads"},{"x-rs-certificate-observed-errors":"none","cs-categories":"Business/Economy;Web Ads/Analytics","c-ip":"192.168.1.1","cs(Referer)":null,"x-rs-certificate-hostname":"*.example.com","sc-bytes":0,"x-rs-ocsp-error":null,"s-supplier-ip":"192.168.1.1","date":[2018,2,2],"x-rs-certificate-hostname-category":"Business/Economy","cs(User-Agent)":null,"cs(Accept-Language)":null,"cs-host":"nqs-nl1-c2.example.com","x-cs-connection-negotiated-ssl-version":"TLSv1","cs-ip":"192.168.1.1","sc-status":0,"x-cs-connection-negotiated-cipher-strength":"high","cs-method":"unknown","x-exception-id":"tenant.content_filter_denied","time":[18,31,18],"x-bluecoat-reference-id":"WA-LS-D_Standard-Deny2","x-bluecoat-application-name":"none","cs-uri-port":443,"s-supplier-failures":null,"rs(Content-Type)":null,"x-rs-certificate-hostname-threat-risk":"unavailable","x-rs-connection-negotiated-cipher-strength":"high","time-taken":1.0,"cs-uri-scheme":"ssl","x-virus-id":null,"s-ip":"192.168.1.1","cs-threat-risk":"unavailable","s-supplier-name":"nqs-nl1-c2.example.com","cs-auth-group":null,"c-connect-type":"Transparent","s-supplier-country":"None","x-cs-ocsp-error":null,"sc-filter-result":"DENIED","cs-username":null,"cs-uri-extension":null,"cs-bytes":0,"x-bluecoat-application-operation":"none","s-action":"DENIED"},{"s-supplier-failures":null,"x-rs-certificate-hostname":"*.mnet-ad.net","c-connect-type":"Transparent","cs-categories":"Web Ads/Analytics","x-bluecoat-application-operation":"none","cs(Accept-Language)":null,"cs-auth-group":null,"x-rs-certificate-hostname-category":"Web Ads/Analytics","x-rs-ocsp-error":null,"c-ip":"192.168.1.1","x-cs-connection-negotiated-cipher-strength":"high","cs-uri-extension":null,"x-exception-id":"tenant.content_filter_denied","cs-host":"s.mnet-ad.net","rs(Content-Type)":null,"date":[2018,2,2],"sc-bytes":0,"x-bluecoat-application-name":"none","x-rs-certificate-hostname-threat-risk":"unavailable","cs-threat-risk":"unavailable","cs-uri-port":443,"x-rs-certificate-observed-errors":"none","s-supplier-name":"s.mnet-ad.net","cs-ip":"192.168.1.1","s-supplier-country":"None","cs-uri-scheme":"ssl","x-virus-id":null,"cs(User-Agent)":null,"cs-bytes":0,"time-taken":1.0,"cs(Referer)":null,"x-bluecoat-reference-id":"WA-LS-D_Standard-Deny2","x-rs-connection-negotiated-cipher-strength":"high","x-cs-ocsp-error":null,"cs-method":"unknown","sc-status":0,"s-action":"DENIED","sc-filter-result":"DENIED","s-ip":"192.168.1.1","time":[18,31,18],"s-supplier-ip":"192.168.1.1","cs-username":null,"x-cs-connection-negotiated-ssl-version":"TLSv1.2"},{"x-bluecoat-application-name":"none","cs-uri-port":443,"cs-uri-scheme":"ssl","time":[18,31,18],"cs-uri-extension":null,"cs-auth-group":null,"cs(Accept-Language)":null,"time-taken":1.0,"cs-ip":"192.168.1.1","x-bluecoat-reference-id":"WA-LS-D_Standard-Deny2","cs-categories":"Web Ads/Analytics","s-action":"DENIED","cs-bytes":0,"cs-username":null,"x-cs-connection-negotiated-ssl-version":"TLSv1.2","s-ip":"192.168.1.1","sc-bytes":0,"cs(User-Agent)":null,"x-bluecoat-application-operation":"none","x-rs-certificate-hostname":"*.mnet-ad.net","c-connect-type":"Transparent","x-rs-certificate-hostname-threat-risk":"unavailable","cs-threat-risk":"unavailable","sc-filter-result":"DENIED","x-exception-id":"tenant.content_filter_denied","rs(Content-Type)":null,"cs-method":"unknown","x-rs-connection-negotiated-cipher-strength":"high","s-supplier-failures":null,"sc-status":0,"c-ip":"192.168.1.1","s-supplier-name":"s.mnet-ad.net","x-cs-ocsp-error":null,"x-rs-certificate-hostname-category":"Web Ads/Analytics","x-rs-ocsp-error":null,"cs-host":"s.mnet-ad.net","x-rs-certificate-observed-errors":"none","x-virus-id":null,"s-supplier-ip":"192.168.1.1","x-cs-connection-negotiated-cipher-strength":"high","s-supplier-country":"None","cs(Referer)":null,"date":[2018,2,2]},{"x-cs-connection-negotiated-cipher-strength":"high","s-supplier-name":"otf.msn.com","time-taken":1.0,"s-supplier-failures":null,"c-connect-type":"Transparent","s-action":"DENIED","cs-threat-risk":"unavailable","x-bluecoat-application-name":"none","cs-auth-group":null,"s-supplier-country":"None","cs(User-Agent)":null,"x-rs-connection-negotiated-cipher-strength":"high","x-rs-certificate-observed-errors":"none","x-rs-ocsp-error":null,"cs(Accept-Language)":null,"s-ip":"192.168.1.1","x-exception-id":"tenant.content_filter_denied","x-bluecoat-reference-id":"WA-LS-D_Standard-Deny2","sc-status":0,"cs-categories":"Web Ads/Analytics","x-rs-certificate-hostname-category":"Search Engines/Portals","c-ip":"192.168.1.1","cs-bytes":0,"x-cs-connection-negotiated-ssl-version":"TLSv1","s-supplier-ip":"192.168.1.1","time":[18,31,18],"x-cs-ocsp-error":null,"x-bluecoat-application-operation":"none","x-rs-certificate-hostname":"udc.msn.com","cs-ip":"192.168.1.1","cs-method":"unknown","sc-filter-result":"DENIED","x-rs-certificate-hostname-threat-risk":"unavailable","cs-username":null,"rs(Content-Type)":null,"cs(Referer)":null,"cs-uri-extension":null,"cs-uri-scheme":"ssl","cs-uri-port":443,"date":[2018,2,2],"cs-host":"otf.msn.com","x-virus-id":null,"sc-bytes":0},{"cs-method":"unknown","cs-uri-extension":null,"cs-uri-port":443,"x-rs-certificate-hostname-category":"Search Engines/Portals","time-taken":1.0,"x-cs-connection-negotiated-ssl-version":"TLSv1","s-supplier-country":"None","x-rs-ocsp-error":null,"cs(User-Agent)":null,"sc-status":0,"cs-threat-risk":"unavailable","cs-username":null,"cs(Accept-Language)":null,"x-virus-id":null,"s-supplier-name":"otf.msn.com","x-bluecoat-reference-id":"WA-LS-D_Standard-Deny2","s-ip":"192.168.1.1","sc-filter-result":"DENIED","x-cs-ocsp-error":null,"s-action":"DENIED","cs-ip":"192.168.1.1","x-rs-certificate-hostname-threat-risk":"unavailable","cs-host":"otf.msn.com","rs(Content-Type)":null,"cs-auth-group":null,"s-supplier-ip":"192.168.1.1","sc-bytes":0,"cs(Referer)":null,"x-bluecoat-application-operation":"none","x-exception-id":"tenant.content_filter_denied","x-rs-connection-negotiated-cipher-strength":"high","x-rs-certificate-observed-errors":"none","time":[18,31,18],"s-supplier-failures":null,"cs-uri-scheme":"ssl","x-cs-connection-negotiated-cipher-strength":"high","c-ip":"192.168.1.1","cs-categories":"Web Ads/Analytics","x-rs-certificate-hostname":"udc.msn.com","cs-bytes":0,"date":[2018,2,2],"x-bluecoat-application-name":"none","c-connect-type":"Transparent"},{"x-bluecoat-application-name":"none","x-rs-connection-negotiated-cipher-strength":"high","sc-bytes":0,"s-supplier-country":"None","cs(Accept-Language)":null,"cs-host":"play.google.com","s-ip":"192.168.1.1","x-cs-connection-negotiated-ssl-version":"TLSv1.2","x-cs-ocsp-error":null,"x-rs-certificate-hostname-category":"Search Engines/Portals","date":[2018,2,2],"x-cs-connection-negotiated-cipher-strength":"high","x-rs-certificate-hostname":"*.google.com","cs-auth-group":null,"sc-filter-result":"DENIED","s-supplier-failures":null,"cs(User-Agent)":null,"cs-threat-risk":"unavailable","c-connect-type":"Transparent","s-supplier-name":"play.google.com","x-rs-certificate-observed-errors":"none","c-ip":"192.168.1.1","cs-uri-port":443,"cs-categories":"Shopping;Software Downloads","x-rs-certificate-hostname-threat-risk":"unavailable","rs(Content-Type)":null,"x-bluecoat-reference-id":"WA-LS-D_Standard-Deny2","cs-bytes":0,"cs-ip":"192.168.1.1","cs-uri-extension":null,"x-virus-id":null,"cs(Referer)":null,"x-rs-ocsp-error":null,"x-exception-id":"tenant.content_filter_denied","s-action":"DENIED","x-bluecoat-application-operation":"none","cs-username":null,"cs-method":"unknown","cs-uri-scheme":"ssl","time":[18,31,18],"sc-status":0,"time-taken":1.0,"s-supplier-ip":"192.168.1.1"},{"cs(Accept-Language)":null,"x-rs-certificate-observed-errors":"none","c-ip":"192.168.1.1","s-action":"DENIED","cs-uri-port":443,"sc-filter-result":"DENIED","cs(User-Agent)":null,"s-supplier-failures":null,"x-cs-connection-negotiated-cipher-strength":"high","x-rs-certificate-hostname-threat-risk":"unavailable","x-bluecoat-application-operation":"none","x-cs-ocsp-error":null,"cs-method":"unknown","cs-categories":"Shopping;Software Downloads","x-exception-id":"tenant.content_filter_denied","c-connect-type":"Transparent","x-rs-certificate-hostname-category":"Search Engines/Portals","sc-status":0,"x-rs-connection-negotiated-cipher-strength":"high","sc-bytes":0,"x-virus-id":null,"rs(Content-Type)":null,"x-rs-ocsp-error":null,"cs-bytes":0,"cs-username":null,"x-bluecoat-application-name":"none","cs-uri-extension":null,"cs-threat-risk":"unavailable","x-cs-connection-negotiated-ssl-version":"TLSv1","cs(Referer)":null,"s-supplier-country":"None","cs-uri-scheme":"ssl","time":[18,31,58],"time-taken":1.0,"cs-ip":"192.168.1.1","cs-host":"play.google.com","x-bluecoat-reference-id":"WA-LS-D_Standard-Deny2","s-ip":"192.168.1.1","x-rs-certificate-hostname":"*.google.com","s-supplier-name":"play.google.com","cs-auth-group":null,"s-supplier-ip":"192.168.1.1","date":[2018,2,2]},{"time-taken":1.0,"time":[18,31,58],"cs-uri-port":443,"cs-host":"play.google.com","s-action":"DENIED","x-virus-id":null,"sc-bytes":0,"x-rs-connection-negotiated-cipher-strength":"high","cs-auth-group":null,"s-ip":"192.168.1.1","x-rs-ocsp-error":null,"cs(Accept-Language)":null,"cs-method":"unknown","s-supplier-country":"None","x-exception-id":"tenant.content_filter_denied","date":[2018,2,2],"cs(Referer)":null,"sc-filter-result":"DENIED","cs-username":null,"x-bluecoat-reference-id":"WA-LS-D_Standard-Deny2","x-rs-certificate-observed-errors":"none","s-supplier-name":"play.google.com","sc-status":0,"cs-threat-risk":"unavailable","x-rs-certificate-hostname-category":"Search Engines/Portals","cs-ip":"192.168.1.1","c-ip":"192.168.1.1","x-bluecoat-application-operation":"none","x-cs-ocsp-error":null,"s-supplier-ip":"192.168.1.1","rs(Content-Type)":null,"cs-categories":"Shopping;Software Downloads","x-cs-connection-negotiated-cipher-strength":"high","cs-bytes":0,"x-rs-certificate-hostname":"*.google.com","c-connect-type":"Transparent","cs-uri-extension":null,"cs(User-Agent)":null,"cs-uri-scheme":"ssl","s-supplier-failures":null,"x-bluecoat-application-name":"none","x-rs-certificate-hostname-threat-risk":"unavailable","x-cs-connection-negotiated-ssl-version":"TLSv1"},{"x-exception-id":"tenant.content_filter_denied","cs-auth-group":null,"x-cs-connection-negotiated-ssl-version":"TLSv1","s-action":"DENIED","cs(User-Agent)":null,"s-supplier-name":"play.google.com","cs-uri-port":443,"x-bluecoat-reference-id":"WA-LS-D_Standard-Deny2","cs(Accept-Language)":null,"cs-uri-scheme":"ssl","c-ip":"192.168.1.1","x-cs-connection-negotiated-cipher-strength":"high","cs-username":null,"date":[2018,2,2],"x-virus-id":null,"s-supplier-country":"None","cs-ip":"192.168.1.1","sc-status":0,"cs-threat-risk":"unavailable","x-rs-certificate-hostname-category":"Search Engines/Portals","cs-host":"play.google.com","time-taken":1.0,"x-rs-certificate-observed-errors":"none","cs-uri-extension":null,"x-rs-certificate-hostname":"*.google.com","x-rs-connection-negotiated-cipher-strength":"high","x-rs-ocsp-error":null,"x-rs-certificate-hostname-threat-risk":"unavailable","c-connect-type":"Transparent","cs-bytes":0,"sc-filter-result":"DENIED","x-cs-ocsp-error":null,"sc-bytes":0,"s-supplier-failures":null,"x-bluecoat-application-operation":"none","rs(Content-Type)":null,"x-bluecoat-application-name":"none","cs-categories":"Shopping;Software Downloads","cs-method":"unknown","cs(Referer)":null,"s-ip":"192.168.1.1","s-supplier-ip":"192.168.1.1","time":[18,31,58]},{"x-rs-certificate-hostname-threat-risk":"unavailable","cs-threat-risk":"unavailable","cs-ip":"192.168.1.1","rs(Content-Type)":null,"x-rs-certificate-hostname-category":"Search Engines/Portals","x-rs-certificate-observed-errors":"none","x-rs-certificate-hostname":"udc.msn.com","sc-status":0,"x-rs-ocsp-error":null,"x-bluecoat-reference-id":"WA-LS-D_Standard-Deny2","x-exception-id":"tenant.content_filter_denied","cs-host":"otf.msn.com","x-rs-connection-negotiated-cipher-strength":"high","cs-categories":"Web Ads/Analytics","sc-filter-result":"DENIED","cs-bytes":0,"x-cs-ocsp-error":null,"s-supplier-ip":"192.168.1.1","cs(Referer)":null,"s-supplier-country":"None","c-connect-type":"Transparent","s-supplier-failures":null,"time":[18,31,58],"sc-bytes":0,"cs-username":null,"cs-uri-extension":null,"s-ip":"192.168.1.1","cs(Accept-Language)":null,"time-taken":1.0,"s-supplier-name":"otf.msn.com","x-virus-id":null,"cs-uri-scheme":"ssl","cs-method":"unknown","s-action":"DENIED","x-bluecoat-application-operation":"none","x-cs-connection-negotiated-cipher-strength":"high","c-ip":"192.168.1.1","cs-auth-group":null,"cs(User-Agent)":null,"x-bluecoat-application-name":"none","date":[2018,2,2],"x-cs-connection-negotiated-ssl-version":"TLSv1","cs-uri-port":443},{"x-rs-certificate-hostname-category":"Search Engines/Portals","x-cs-ocsp-error":null,"x-rs-certificate-hostname":"udc.msn.com","x-exception-id":"tenant.content_filter_denied","c-ip":"192.168.1.1","x-bluecoat-reference-id":"WA-LS-D_Standard-Deny2","cs-method":"unknown","time":[18,31,58],"c-connect-type":"Transparent","cs-threat-risk":"unavailable","s-supplier-ip":"192.168.1.1","cs-uri-extension":null,"s-action":"DENIED","x-bluecoat-application-operation":"none","x-cs-connection-negotiated-ssl-version":"TLSv1","sc-filter-result":"DENIED","cs(User-Agent)":null,"x-rs-connection-negotiated-cipher-strength":"high","cs-uri-port":443,"cs-host":"otf.msn.com","rs(Content-Type)":null,"cs-bytes":0,"s-ip":"192.168.1.1","cs-auth-group":null,"cs-uri-scheme":"ssl","cs(Accept-Language)":null,"cs-username":null,"cs-ip":"192.168.1.1","x-rs-ocsp-error":null,"cs-categories":"Web Ads/Analytics","s-supplier-failures":null,"sc-bytes":0,"s-supplier-name":"otf.msn.com","time-taken":1.0,"x-bluecoat-application-name":"none","cs(Referer)":null,"sc-status":0,"s-supplier-country":"None","x-cs-connection-negotiated-cipher-strength":"high","date":[2018,2,2],"x-rs-certificate-observed-errors":"none","x-rs-certificate-hostname-threat-risk":"unavailable","x-virus-id":null},{"cs-uri-scheme":"ssl","x-rs-certificate-hostname-threat-risk":"unavailable","x-bluecoat-application-name":"none","cs-bytes":0,"cs-username":null,"x-rs-certificate-hostname":"*.google.com","sc-status":0,"s-supplier-ip":"192.168.1.1","s-supplier-name":"play.google.com","date":[2018,2,2],"x-cs-connection-negotiated-cipher-strength":"high","cs-host":"play.google.com","cs-categories":"Shopping;Software Downloads","cs(Accept-Language)":null,"x-rs-certificate-observed-errors":"none","x-rs-connection-negotiated-cipher-strength":"high","sc-bytes":0,"x-bluecoat-application-operation":"none","c-connect-type":"Transparent","c-ip":"192.168.1.1","x-rs-ocsp-error":null,"x-rs-certificate-hostname-category":"Search Engines/Portals","s-supplier-failures":null,"x-virus-id":null,"cs(User-Agent)":null,"rs(Content-Type)":null,"x-cs-connection-negotiated-ssl-version":"TLSv1.2","cs-auth-group":null,"time":[18,31,58],"x-bluecoat-reference-id":"WA-LS-D_Standard-Deny2","cs-ip":"192.168.1.1","s-ip":"192.168.1.1","x-exception-id":"tenant.content_filter_denied","s-supplier-country":"None","sc-filter-result":"DENIED","cs-method":"unknown","cs-uri-extension":null,"time-taken":1.0,"x-cs-ocsp-error":null,"cs-uri-port":443,"cs(Referer)":null,"cs-threat-risk":"unavailable","s-action":"DENIED"},{"cs-host":"client.wns.windows.com","x-rs-certificate-hostname-threat-risk":"unavailable","s-supplier-name":"client.wns.windows.com","cs-uri-port":443,"cs-bytes":1669,"c-connect-type":"Transparent","sc-status":0,"s-supplier-country":"None","cs(User-Agent)":null,"x-rs-certificate-hostname-category":"Technology/Internet","cs-threat-risk":"unavailable","s-action":"TUNNELED","cs-uri-scheme":"ssl","x-rs-certificate-observed-errors":"none","x-cs-connection-negotiated-cipher-strength":"high","cs-ip":"192.168.1.1","date":[2018,2,2],"cs-uri-extension":null,"cs-username":null,"sc-filter-result":"OBSERVED","x-rs-connection-negotiated-cipher-strength":"high","x-cs-connection-negotiated-ssl-version":"TLSv1.2","x-virus-id":null,"x-bluecoat-reference-id":"WA-SP-A_Standard-Allow","x-exception-id":null,"rs(Content-Type)":null,"x-bluecoat-application-operation":"none","cs-auth-group":null,"time":[18,31,58],"cs-categories":"Technology/Internet","cs(Accept-Language)":null,"cs-method":"unknown","sc-bytes":332,"x-cs-ocsp-error":null,"cs(Referer)":null,"s-supplier-failures":null,"c-ip":"192.168.1.1","s-ip":"192.168.1.1","time-taken":615.0,"s-supplier-ip":"192.168.1.1","x-bluecoat-application-name":"none","x-rs-certificate-hostname":"*.wns.windows.com","x-rs-ocsp-error":null},{"x-bluecoat-reference-id":"WA-LS-D_Standard-Deny2","s-supplier-failures":null,"x-rs-certificate-observed-errors":"none","x-rs-certificate-hostname":"*.scorecardresearch.com","s-action":"DENIED","sc-status":0,"c-connect-type":"Transparent","rs(Content-Type)":null,"x-rs-certificate-hostname-threat-risk":"unavailable","cs-uri-scheme":"ssl","date":[2018,2,2],"c-ip":"192.168.1.1","cs-auth-group":null,"cs-threat-risk":"unavailable","x-rs-ocsp-error":null,"s-ip":"192.168.1.1","cs-bytes":0,"x-rs-connection-negotiated-cipher-strength":"high","sc-filter-result":"DENIED","time":[18,31,58],"cs-categories":"Web Ads/Analytics","x-bluecoat-application-name":"none","x-rs-certificate-hostname-category":"Business/Economy","cs-username":null,"s-supplier-country":"None","cs(Accept-Language)":null,"cs(User-Agent)":null,"x-cs-connection-negotiated-cipher-strength":"high","x-cs-ocsp-error":null,"cs(Referer)":null,"s-supplier-name":"sb.scorecardresearch.com","cs-host":"sb.scorecardresearch.com","s-supplier-ip":"192.168.1.1","x-exception-id":"tenant.content_filter_denied","cs-uri-port":443,"time-taken":1.0,"cs-ip":"192.168.1.1","sc-bytes":0,"x-virus-id":null,"cs-method":"unknown","x-cs-connection-negotiated-ssl-version":"TLSv1.2","cs-uri-extension":null,"x-bluecoat-application-operation":"none"},{"sc-status":0,"x-rs-certificate-hostname":"*.wns.windows.com","sc-filter-result":"OBSERVED","date":[2018,2,2],"rs(Content-Type)":null,"x-cs-connection-negotiated-ssl-version":"TLSv1.2","s-supplier-country":"None","x-bluecoat-application-operation":"none","cs-threat-risk":"unavailable","x-virus-id":null,"cs-uri-port":443,"cs-auth-group":null,"cs-ip":"192.168.1.1","x-rs-connection-negotiated-cipher-strength":"high","time":[18,31,58],"cs-uri-scheme":"ssl","sc-bytes":332,"s-ip":"192.168.1.1","cs-bytes":1704,"x-rs-certificate-hostname-category":"Technology/Internet","cs(Accept-Language)":null,"s-supplier-failures":null,"x-exception-id":null,"x-rs-certificate-observed-errors":"none","time-taken":271.0,"cs-username":null,"c-connect-type":"Transparent","x-bluecoat-reference-id":"WA-SP-A_Standard-Allow","cs-uri-extension":null,"cs(Referer)":null,"x-rs-ocsp-error":null,"s-supplier-ip":"192.168.1.1","x-cs-connection-negotiated-cipher-strength":"high","x-rs-certificate-hostname-threat-risk":"unavailable","c-ip":"192.168.1.1","s-action":"TUNNELED","cs(User-Agent)":null,"x-cs-ocsp-error":null,"s-supplier-name":"client.wns.windows.com","cs-host":"client.wns.windows.com","x-bluecoat-application-name":"none","cs-categories":"Technology/Internet","cs-method":"unknown"},{"x-exception-id":"tenant.content_filter_denied","cs-categories":"Shopping;Software Downloads","time":[18,31,58],"cs(Accept-Language)":null,"c-connect-type":"Transparent","x-rs-connection-negotiated-cipher-strength":"high","x-bluecoat-application-name":"none","cs(Referer)":null,"x-bluecoat-application-operation":"none","x-bluecoat-reference-id":"WA-LS-D_Standard-Deny2","cs-uri-scheme":"ssl","x-cs-connection-negotiated-ssl-version":"TLSv1.2","date":[2018,2,2],"sc-bytes":0,"cs-uri-port":443,"cs-ip":"192.168.1.1","s-supplier-ip":"192.168.1.1","rs(Content-Type)":null,"s-supplier-name":"play.google.com","cs-uri-extension":null,"c-ip":"192.168.1.1","cs-bytes":0,"cs-username":null,"x-cs-connection-negotiated-cipher-strength":"high","cs-threat-risk":"unavailable","sc-filter-result":"DENIED","s-supplier-country":"None","s-supplier-failures":null,"x-rs-certificate-hostname-threat-risk":"unavailable","x-rs-certificate-hostname-category":"Search Engines/Portals","x-rs-certificate-hostname":"*.google.com","s-ip":"192.168.1.1","cs-method":"unknown","x-cs-ocsp-error":null,"x-virus-id":null,"cs(User-Agent)":null,"time-taken":1.0,"cs-host":"play.google.com","sc-status":0,"s-action":"DENIED","x-rs-certificate-observed-errors":"none","x-rs-ocsp-error":null,"cs-auth-group":null},{"x-bluecoat-application-operation":"none","sc-filter-result":"OBSERVED","x-bluecoat-reference-id":"WA-SP-A_Standard-Allow","x-rs-certificate-hostname-category":"Radio/Audio Streams","cs(Accept-Language)":null,"cs-auth-group":null,"sc-status":0,"x-rs-certificate-hostname-threat-risk":"unavailable","s-supplier-failures":null,"cs-threat-risk":"unavailable","x-cs-ocsp-error":null,"cs-host":"api.spotify.com","x-rs-certificate-hostname":"*.spotify.com","cs-uri-extension":null,"cs-bytes":3479,"x-rs-connection-negotiated-cipher-strength":"high","sc-bytes":2573,"s-supplier-country":"None","x-rs-ocsp-error":null,"s-action":"TUNNELED","x-cs-connection-negotiated-cipher-strength":"high","time":[18,31,58],"x-virus-id":null,"cs(Referer)":null,"cs-ip":"192.168.1.1","time-taken":31946.0,"cs-uri-scheme":"ssl","s-supplier-ip":"192.168.1.1","cs-method":"unknown","c-ip":"192.168.1.1","rs(Content-Type)":null,"x-rs-certificate-observed-errors":"none","cs-categories":"Radio/Audio Streams;Entertainment","cs-username":null,"x-exception-id":null,"s-supplier-name":"api.spotify.com","c-connect-type":"Transparent","cs-uri-port":443,"date":[2018,2,2],"x-cs-connection-negotiated-ssl-version":"TLSv1.2","s-ip":"192.168.1.1","cs(User-Agent)":null,"x-bluecoat-application-name":"none"},{"x-rs-certificate-hostname-threat-risk":"unavailable","time":[18,31,58],"x-bluecoat-application-name":"none","x-rs-connection-negotiated-cipher-strength":"high","s-action":"TUNNELED","x-rs-ocsp-error":null,"cs-uri-port":443,"sc-status":0,"c-connect-type":"Transparent","cs-host":"open.spotify.com","cs-uri-extension":null,"x-rs-certificate-hostname-category":"Radio/Audio Streams","x-cs-connection-negotiated-cipher-strength":"high","c-ip":"192.168.1.1","cs-threat-risk":"unavailable","date":[2018,2,2],"cs-ip":"192.168.1.1","x-bluecoat-reference-id":"WA-SP-A_Standard-Allow","cs(Accept-Language)":null,"cs-uri-scheme":"ssl","s-supplier-ip":"192.168.1.1","s-supplier-failures":null,"x-bluecoat-application-operation":"none","x-cs-connection-negotiated-ssl-version":"TLSv1.2","cs-bytes":2976,"cs-auth-group":null,"cs(User-Agent)":null,"cs-username":null,"cs(Referer)":null,"x-cs-ocsp-error":null,"sc-filter-result":"OBSERVED","time-taken":33207.0,"s-supplier-name":"open.spotify.com","x-rs-certificate-hostname":"*.spotify.com","x-rs-certificate-observed-errors":"none","s-ip":"192.168.1.1","sc-bytes":2075,"x-exception-id":null,"s-supplier-country":"None","cs-categories":"Radio/Audio Streams;Entertainment","cs-method":"unknown","rs(Content-Type)":null,"x-virus-id":null},{"x-virus-id":null,"cs(Referer)":null,"cs-uri-port":443,"sc-status":0,"cs-uri-scheme":"ssl","x-rs-ocsp-error":null,"cs(User-Agent)":null,"time":[18,31,58],"x-rs-certificate-observed-errors":"none","date":[2018,2,2],"x-rs-connection-negotiated-cipher-strength":"high","cs-bytes":1302,"rs(Content-Type)":null,"cs-ip":"192.168.1.1","x-bluecoat-application-name":"none","s-supplier-failures":null,"s-supplier-name":"api.spotify.com","s-action":"TUNNELED","x-bluecoat-application-operation":"none","x-rs-certificate-hostname":"*.spotify.com","sc-bytes":1842,"s-supplier-ip":"192.168.1.1","x-bluecoat-reference-id":"WA-SP-A_Standard-Allow","s-supplier-country":"None","cs-method":"unknown","cs-auth-group":null,"time-taken":32020.0,"cs-host":"api.spotify.com","x-exception-id":null,"c-connect-type":"Transparent","s-ip":"192.168.1.1","x-cs-connection-negotiated-ssl-version":"TLSv1.2","cs(Accept-Language)":null,"cs-categories":"Radio/Audio Streams;Entertainment","cs-username":null,"x-cs-ocsp-error":null,"sc-filter-result":"OBSERVED","cs-uri-extension":null,"x-rs-certificate-hostname-category":"Radio/Audio Streams","x-rs-certificate-hostname-threat-risk":"unavailable","x-cs-connection-negotiated-cipher-strength":"high","c-ip":"192.168.1.1","cs-threat-risk":"unavailable"},{"x-cs-ocsp-error":null,"sc-status":0,"x-bluecoat-application-operation":"none","cs-uri-scheme":"ssl","x-cs-connection-negotiated-ssl-version":"TLSv1","x-rs-certificate-hostname-threat-risk":"unavailable","cs-host":"www.google-analytics.com","cs-uri-port":443,"x-virus-id":null,"s-supplier-failures":null,"x-cs-connection-negotiated-cipher-strength":"high","s-action":"DENIED","s-supplier-country":"None","x-bluecoat-reference-id":"WA-LS-D_Standard-Deny2","cs-bytes":0,"s-supplier-ip":"192.168.1.1","cs-categories":"Web Ads/Analytics","s-ip":"192.168.1.1","x-exception-id":"tenant.content_filter_denied","cs(Accept-Language)":null,"cs-username":null,"x-bluecoat-application-name":"none","sc-bytes":0,"time-taken":1.0,"cs(User-Agent)":null,"x-rs-certificate-hostname":"*.google-analytics.com","c-connect-type":"Transparent","x-rs-certificate-observed-errors":"none","cs-ip":"192.168.1.1","date":[2018,2,2],"cs-auth-group":null,"cs-method":"unknown","s-supplier-name":"www.google-analytics.com","x-rs-connection-negotiated-cipher-strength":"high","sc-filter-result":"DENIED","time":[18,31,58],"c-ip":"192.168.1.1","cs-uri-extension":null,"rs(Content-Type)":null,"x-rs-ocsp-error":null,"x-rs-certificate-hostname-category":"Web Ads/Analytics","cs(Referer)":null,"cs-threat-risk":"unavailable"},{"cs-threat-risk":"unavailable","s-action":"DENIED","cs-auth-group":null,"sc-filter-result":"DENIED","s-supplier-country":"None","cs-username":null,"x-rs-certificate-hostname-category":"Search Engines/Portals","s-supplier-ip":"192.168.1.1","x-cs-ocsp-error":null,"cs-method":"unknown","x-rs-ocsp-error":null,"x-bluecoat-application-name":"none","x-rs-certificate-observed-errors":"none","cs-categories":"Shopping;Software Downloads","sc-bytes":0,"x-exception-id":"tenant.content_filter_denied","x-cs-connection-negotiated-ssl-version":"TLSv1","time-taken":1.0,"x-virus-id":null,"cs(Accept-Language)":null,"cs-uri-port":443,"x-cs-connection-negotiated-cipher-strength":"high","rs(Content-Type)":null,"x-bluecoat-application-operation":"none","cs-ip":"192.168.1.1","s-supplier-failures":null,"x-rs-certificate-hostname-threat-risk":"unavailable","cs-uri-scheme":"ssl","cs-host":"play.google.com","cs(Referer)":null,"s-supplier-name":"play.google.com","c-connect-type":"Transparent","cs-uri-extension":null,"x-rs-certificate-hostname":"*.google.com","cs(User-Agent)":null,"s-ip":"192.168.1.1","date":[2018,2,2],"cs-bytes":0,"x-rs-connection-negotiated-cipher-strength":"high","time":[18,31,58],"sc-status":0,"c-ip":"192.168.1.1","x-bluecoat-reference-id":"WA-LS-D_Standard-Deny2"},{"c-connect-type":"Transparent","x-rs-certificate-observed-errors":"none","cs-bytes":0,"x-virus-id":null,"sc-filter-result":"DENIED","sc-bytes":0,"x-bluecoat-application-operation":"none","cs(User-Agent)":null,"rs(Content-Type)":null,"cs-categories":"Shopping;Software Downloads","cs-method":"unknown","cs-ip":"192.168.1.1","x-cs-connection-negotiated-cipher-strength":"high","cs-host":"play.google.com","cs-auth-group":null,"cs-uri-port":443,"cs-uri-extension":null,"x-rs-certificate-hostname":"*.google.com","s-ip":"192.168.1.1","x-rs-certificate-hostname-threat-risk":"unavailable","x-rs-connection-negotiated-cipher-strength":"high","s-supplier-country":"None","s-action":"DENIED","x-cs-connection-negotiated-ssl-version":"TLSv1","s-supplier-name":"play.google.com","c-ip":"192.168.1.1","cs(Referer)":null,"sc-status":0,"s-supplier-ip":"192.168.1.1","time":[18,31,58],"cs-uri-scheme":"ssl","cs(Accept-Language)":null,"x-bluecoat-reference-id":"WA-LS-D_Standard-Deny2","x-rs-ocsp-error":null,"x-rs-certificate-hostname-category":"Search Engines/Portals","x-exception-id":"tenant.content_filter_denied","s-supplier-failures":null,"time-taken":1.0,"cs-username":null,"x-bluecoat-application-name":"none","x-cs-ocsp-error":null,"date":[2018,2,2],"cs-threat-risk":"unavailable"},{"x-bluecoat-application-operation":"none","sc-bytes":129,"x-rs-certificate-observed-errors":"none","cs-uri-extension":null,"sc-filter-result":"OBSERVED","cs-method":"unknown","x-rs-certificate-hostname":"*.wns.windows.com","time":[18,31,58],"x-exception-id":null,"cs-username":null,"cs(User-Agent)":null,"date":[2018,2,2],"cs-host":"db5sch101110105.wns.windows.com","cs-uri-scheme":"ssl","time-taken":21086.0,"x-bluecoat-application-name":"none","x-cs-ocsp-error":null,"x-virus-id":null,"s-ip":"192.168.1.1","c-ip":"192.168.1.1","x-rs-ocsp-error":null,"x-bluecoat-reference-id":"WA-SP-A_Standard-Allow","x-cs-connection-negotiated-ssl-version":"TLSv1.2","x-rs-connection-negotiated-cipher-strength":"high","s-supplier-name":"db5sch101110105.wns.windows.com","s-action":"TUNNELED","x-rs-certificate-hostname-threat-risk":"unavailable","cs-auth-group":null,"cs-ip":"192.168.1.1","cs(Accept-Language)":null,"s-supplier-country":"None","cs-bytes":550,"cs-threat-risk":"unavailable","x-cs-connection-negotiated-cipher-strength":"high","sc-status":0,"cs(Referer)":null,"s-supplier-failures":null,"cs-categories":"Technology/Internet","s-supplier-ip":"192.168.1.1","rs(Content-Type)":null,"c-connect-type":"Transparent","cs-uri-port":443,"x-rs-certificate-hostname-category":"Technology/Internet"},{"cs-uri-extension":null,"x-rs-certificate-hostname-threat-risk":"unavailable","sc-filter-result":"OBSERVED","cs-method":"unknown","cs-uri-port":443,"cs-categories":"Technology/Internet","cs-ip":"192.168.1.1","s-supplier-name":"client.wns.windows.com","time-taken":188.0,"time":[18,31,59],"c-ip":"192.168.1.1","x-rs-certificate-hostname-category":"Technology/Internet","cs(User-Agent)":null,"x-rs-certificate-hostname":"*.wns.windows.com","sc-bytes":332,"x-bluecoat-application-name":"none","cs-bytes":1660,"x-cs-connection-negotiated-cipher-strength":"high","cs-uri-scheme":"ssl","x-cs-ocsp-error":null,"x-cs-connection-negotiated-ssl-version":"TLSv1.2","cs(Referer)":null,"x-rs-connection-negotiated-cipher-strength":"high","x-rs-ocsp-error":null,"date":[2018,2,2],"sc-status":0,"rs(Content-Type)":null,"cs-host":"client.wns.windows.com","s-supplier-country":"None","cs(Accept-Language)":null,"x-bluecoat-reference-id":"WA-SP-A_Standard-Allow","x-exception-id":null,"x-bluecoat-application-operation":"none","x-rs-certificate-observed-errors":"none","s-action":"TUNNELED","s-supplier-ip":"192.168.1.1","s-supplier-failures":null,"s-ip":"192.168.1.1","cs-threat-risk":"unavailable","x-virus-id":null,"c-connect-type":"Transparent","cs-auth-group":null,"cs-username":null},{"x-cs-connection-negotiated-cipher-strength":"high","x-bluecoat-application-operation":"none","x-rs-certificate-hostname-threat-risk":"unavailable","s-ip":"192.168.1.1","time":[18,31,59],"x-exception-id":null,"x-rs-ocsp-error":null,"cs-categories":"Technology/Internet","x-cs-ocsp-error":null,"date":[2018,2,2],"x-rs-certificate-hostname-category":"Technology/Internet","x-rs-certificate-observed-errors":"none","cs(Accept-Language)":null,"cs(Referer)":null,"cs(User-Agent)":null,"cs-method":"unknown","cs-uri-extension":null,"cs-auth-group":null,"cs-uri-scheme":"ssl","x-bluecoat-application-name":"none","cs-host":"client.wns.windows.com","x-rs-connection-negotiated-cipher-strength":"high","x-bluecoat-reference-id":"WA-SP-A_Standard-Allow","sc-status":0,"c-connect-type":"Transparent","cs-uri-port":443,"s-supplier-name":"client.wns.windows.com","rs(Content-Type)":null,"x-cs-connection-negotiated-ssl-version":"TLSv1.2","s-action":"TUNNELED","cs-username":null,"s-supplier-country":"None","sc-filter-result":"OBSERVED","time-taken":324.0,"cs-ip":"192.168.1.1","x-virus-id":null,"cs-bytes":1680,"sc-bytes":332,"c-ip":"192.168.1.1","s-supplier-ip":"192.168.1.1","s-supplier-failures":null,"cs-threat-risk":"unavailable","x-rs-certificate-hostname":"*.wns.windows.com"},{"cs-auth-group":null,"x-rs-ocsp-error":null,"x-cs-connection-negotiated-cipher-strength":"high","cs-method":"unknown","x-virus-id":null,"s-action":"DENIED","x-cs-connection-negotiated-ssl-version":"TLSv1","sc-status":0,"cs-threat-risk":"unavailable","c-connect-type":"Transparent","cs(Accept-Language)":null,"sc-filter-result":"DENIED","cs-username":null,"x-rs-certificate-hostname-category":"Search Engines/Portals","cs-uri-scheme":"ssl","x-exception-id":"tenant.content_filter_denied","s-supplier-name":"play.google.com","x-bluecoat-application-name":"none","cs-categories":"Shopping;Software Downloads","x-rs-certificate-hostname-threat-risk":"unavailable","cs-ip":"192.168.1.1","x-rs-connection-negotiated-cipher-strength":"high","cs-host":"play.google.com","s-ip":"192.168.1.1","time-taken":1.0,"date":[2018,2,2],"s-supplier-ip":"192.168.1.1","cs(Referer)":null,"x-bluecoat-application-operation":"none","cs-uri-port":443,"s-supplier-country":"None","cs(User-Agent)":null,"s-supplier-failures":null,"cs-bytes":0,"x-rs-certificate-hostname":"*.google.com","time":[18,31,59],"x-cs-ocsp-error":null,"sc-bytes":0,"rs(Content-Type)":null,"x-rs-certificate-observed-errors":"none","cs-uri-extension":null,"c-ip":"192.168.1.1","x-bluecoat-reference-id":"WA-LS-D_Standard-Deny2"},{"sc-filter-result":"DENIED","x-cs-ocsp-error":null,"s-supplier-country":"None","s-supplier-failures":null,"cs(Referer)":null,"x-rs-certificate-observed-errors":"none","s-supplier-ip":"192.168.1.1","x-bluecoat-application-operation":"none","cs-ip":"192.168.1.1","cs-method":"unknown","date":[2018,2,2],"cs-categories":"Shopping;Software Downloads","x-rs-ocsp-error":null,"cs-uri-port":443,"x-bluecoat-application-name":"none","cs-username":null,"cs(User-Agent)":null,"x-rs-connection-negotiated-cipher-strength":"high","cs-host":"play.google.com","s-action":"DENIED","sc-bytes":0,"s-ip":"192.168.1.1","x-bluecoat-reference-id":"WA-LS-D_Standard-Deny2","cs-threat-risk":"unavailable","c-connect-type":"Transparent","x-cs-connection-negotiated-ssl-version":"TLSv1.2","c-ip":"192.168.1.1","time-taken":1.0,"cs-uri-extension":null,"x-rs-certificate-hostname-category":"Search Engines/Portals","x-rs-certificate-hostname":"*.google.com","time":[18,31,59],"cs-auth-group":null,"rs(Content-Type)":null,"cs-uri-scheme":"ssl","cs(Accept-Language)":null,"x-rs-certificate-hostname-threat-risk":"unavailable","cs-bytes":0,"sc-status":0,"x-exception-id":"tenant.content_filter_denied","s-supplier-name":"play.google.com","x-cs-connection-negotiated-cipher-strength":"high","x-virus-id":null},{"sc-filter-result":"DENIED","c-connect-type":"Transparent","time-taken":1.0,"x-rs-certificate-hostname":"*.google.com","cs-uri-scheme":"ssl","x-exception-id":"tenant.content_filter_denied","x-cs-connection-negotiated-ssl-version":"TLSv1","cs(User-Agent)":null,"x-bluecoat-reference-id":"WA-LS-D_Standard-Deny2","x-rs-ocsp-error":null,"cs-bytes":0,"x-cs-connection-negotiated-cipher-strength":"high","cs-uri-port":443,"rs(Content-Type)":null,"x-bluecoat-application-operation":"none","s-ip":"192.168.1.1","date":[2018,2,2],"cs-method":"unknown","x-rs-certificate-observed-errors":"none","s-supplier-country":"None","cs(Accept-Language)":null,"s-supplier-name":"play.google.com","cs(Referer)":null,"cs-host":"play.google.com","x-bluecoat-application-name":"none","cs-ip":"192.168.1.1","sc-status":0,"x-rs-connection-negotiated-cipher-strength":"high","c-ip":"192.168.1.1","cs-categories":"Shopping;Software Downloads","x-rs-certificate-hostname-threat-risk":"unavailable","cs-username":null,"s-supplier-ip":"192.168.1.1","x-rs-certificate-hostname-category":"Search Engines/Portals","cs-uri-extension":null,"x-cs-ocsp-error":null,"cs-auth-group":null,"s-supplier-failures":null,"s-action":"DENIED","x-virus-id":null,"time":[18,31,59],"cs-threat-risk":"unavailable","sc-bytes":0},{"cs-username":null,"x-rs-certificate-hostname-threat-risk":"unavailable","x-virus-id":null,"s-supplier-country":"None","x-cs-connection-negotiated-cipher-strength":"high","x-rs-certificate-hostname":"*.google.com","x-rs-certificate-observed-errors":"none","cs(Referer)":null,"cs-uri-scheme":"ssl","c-ip":"192.168.1.1","s-action":"DENIED","cs(User-Agent)":null,"cs-uri-extension":null,"x-exception-id":"tenant.content_filter_denied","x-bluecoat-application-name":"none","rs(Content-Type)":null,"sc-filter-result":"DENIED","sc-status":0,"x-rs-certificate-hostname-category":"Search Engines/Portals","cs-auth-group":null,"cs-uri-port":443,"cs-host":"play.google.com","x-cs-ocsp-error":null,"cs(Accept-Language)":null,"time":[18,31,59],"date":[2018,2,2],"x-bluecoat-application-operation":"none","cs-ip":"192.168.1.1","c-connect-type":"Transparent","x-rs-ocsp-error":null,"time-taken":2.0,"x-cs-connection-negotiated-ssl-version":"TLSv1.2","x-bluecoat-reference-id":"WA-LS-D_Standard-Deny2","s-supplier-ip":"192.168.1.1","cs-threat-risk":"unavailable","x-rs-connection-negotiated-cipher-strength":"high","s-supplier-name":"play.google.com","cs-categories":"Shopping;Software Downloads","cs-method":"unknown","sc-bytes":0,"s-supplier-failures":null,"s-ip":"192.168.1.1","cs-bytes":0},{"cs-auth-group":null,"cs-uri-port":443,"x-cs-connection-negotiated-cipher-strength":"high","cs-host":"play.google.com","x-rs-certificate-hostname-category":"Search Engines/Portals","s-supplier-country":"None","s-supplier-name":"play.google.com","x-rs-certificate-observed-errors":"none","x-exception-id":"tenant.content_filter_denied","cs(User-Agent)":null,"cs-threat-risk":"unavailable","x-cs-connection-negotiated-ssl-version":"TLSv1","cs-categories":"Shopping;Software Downloads","sc-bytes":0,"cs-ip":"192.168.1.1","x-cs-ocsp-error":null,"cs(Accept-Language)":null,"cs-uri-extension":null,"sc-status":0,"sc-filter-result":"DENIED","x-bluecoat-application-operation":"none","s-ip":"192.168.1.1","cs(Referer)":null,"c-connect-type":"Transparent","s-supplier-failures":null,"x-bluecoat-reference-id":"WA-LS-D_Standard-Deny2","cs-uri-scheme":"ssl","cs-bytes":0,"cs-username":null,"cs-method":"unknown","rs(Content-Type)":null,"time-taken":1.0,"s-action":"DENIED","x-rs-certificate-hostname-threat-risk":"unavailable","s-supplier-ip":"192.168.1.1","time":[18,31,59],"date":[2018,2,2],"x-virus-id":null,"x-rs-ocsp-error":null,"x-rs-connection-negotiated-cipher-strength":"high","x-bluecoat-application-name":"none","x-rs-certificate-hostname":"*.google.com","c-ip":"192.168.1.1"},{"x-exception-id":"tenant.content_filter_denied","cs-uri-scheme":"ssl","s-supplier-failures":null,"c-connect-type":"Transparent","x-cs-ocsp-error":null,"cs-auth-group":null,"cs-username":null,"cs-ip":"192.168.1.1","x-rs-certificate-hostname":"*.google.com","time-taken":1.0,"cs(Accept-Language)":null,"rs(Content-Type)":null,"x-rs-connection-negotiated-cipher-strength":"high","s-supplier-ip":"192.168.1.1","s-supplier-country":"None","cs-method":"unknown","x-bluecoat-application-operation":"none","sc-filter-result":"DENIED","x-rs-certificate-hostname-threat-risk":"unavailable","cs-host":"play.google.com","cs-uri-extension":null,"cs-bytes":0,"x-rs-certificate-hostname-category":"Search Engines/Portals","time":[18,31,59],"s-action":"DENIED","x-rs-certificate-observed-errors":"none","x-bluecoat-reference-id":"WA-LS-D_Standard-Deny2","date":[2018,2,2],"x-virus-id":null,"cs-categories":"Shopping;Software Downloads","x-rs-ocsp-error":null,"s-ip":"192.168.1.1","x-cs-connection-negotiated-ssl-version":"TLSv1","sc-status":0,"sc-bytes":0,"cs(Referer)":null,"x-cs-connection-negotiated-cipher-strength":"high","x-bluecoat-application-name":"none","cs-threat-risk":"unavailable","cs(User-Agent)":null,"c-ip":"192.168.1.1","s-supplier-name":"play.google.com","cs-uri-port":443},{"cs-uri-extension":null,"x-exception-id":"tenant.content_filter_denied","s-action":"DENIED","x-rs-certificate-hostname-threat-risk":"unavailable","x-cs-connection-negotiated-cipher-strength":"high","s-supplier-country":"None","cs-bytes":0,"cs-threat-risk":"unavailable","cs-uri-scheme":"ssl","x-bluecoat-application-operation":null,"time":[18,31,59],"sc-bytes":0,"cs-auth-group":null,"c-ip":"192.168.1.1","sc-filter-result":"DENIED","c-connect-type":"Transparent","cs-method":"unknown","x-rs-ocsp-error":null,"cs-host":"oneclient.sfx.ms","time-taken":1.0,"cs(Referer)":null,"cs-categories":"File Storage/Sharing","x-rs-certificate-hostname":"wildcard.sfx.ms","x-bluecoat-application-name":"Windows Live SkyDrive","sc-status":0,"x-cs-ocsp-error":null,"x-rs-connection-negotiated-cipher-strength":"high","cs(Accept-Language)":null,"cs-uri-port":443,"x-rs-certificate-observed-errors":"none","s-supplier-failures":null,"x-virus-id":null,"x-rs-certificate-hostname-category":"Content Servers","cs(User-Agent)":null,"s-supplier-ip":"192.168.1.1","s-ip":"192.168.1.1","cs-ip":"192.168.1.1","x-cs-connection-negotiated-ssl-version":"TLSv1.2","rs(Content-Type)":null,"cs-username":null,"date":[2018,2,2],"x-bluecoat-reference-id":"WA-LS-D_Standard-Deny2","s-supplier-name":"oneclient.sfx.ms"},{"x-rs-certificate-hostname-threat-risk":"unavailable","s-ip":"192.168.1.1","time":[18,31,59],"x-bluecoat-application-operation":"none","x-cs-connection-negotiated-cipher-strength":"high","cs-uri-extension":null,"cs-categories":"Technology/Internet","cs-host":"db5sch103091510.wns.windows.com","cs-ip":"192.168.1.1","cs-uri-port":443,"date":[2018,2,2],"time-taken":3453.0,"cs(Referer)":null,"sc-bytes":129,"x-bluecoat-application-name":"none","rs(Content-Type)":null,"x-rs-ocsp-error":null,"c-connect-type":"Transparent","cs-uri-scheme":"ssl","x-cs-ocsp-error":null,"x-rs-certificate-hostname":"*.wns.windows.com","x-rs-certificate-observed-errors":"none","x-virus-id":null,"s-supplier-country":"None","sc-status":0,"x-rs-connection-negotiated-cipher-strength":"high","s-supplier-failures":null,"x-cs-connection-negotiated-ssl-version":"TLSv1.2","x-exception-id":null,"cs-bytes":550,"cs-username":null,"cs(Accept-Language)":null,"cs-method":"unknown","sc-filter-result":"OBSERVED","cs-threat-risk":"unavailable","cs-auth-group":null,"x-bluecoat-reference-id":"WA-SP-A_Standard-Allow","s-supplier-ip":"192.168.1.1","s-action":"TUNNELED","c-ip":"192.168.1.1","cs(User-Agent)":null,"x-rs-certificate-hostname-category":"Technology/Internet","s-supplier-name":"db5sch103091510.wns.windows.com"},{"cs-username":null,"cs-uri-port":443,"x-cs-connection-negotiated-ssl-version":"TLSv1.2","x-bluecoat-application-operation":"none","x-bluecoat-application-name":"none","s-supplier-ip":"192.168.1.1","date":[2018,2,2],"cs-bytes":0,"cs-host":"play.google.com","x-rs-certificate-hostname-category":"Search Engines/Portals","sc-filter-result":"DENIED","time":[18,31,59],"x-cs-connection-negotiated-cipher-strength":"high","cs(User-Agent)":null,"cs-uri-extension":null,"cs(Referer)":null,"s-supplier-country":"None","time-taken":1.0,"s-supplier-name":"play.google.com","s-action":"DENIED","c-connect-type":"Transparent","sc-status":0,"x-rs-certificate-observed-errors":"none","sc-bytes":0,"x-rs-certificate-hostname":"*.google.com","x-exception-id":"tenant.content_filter_denied","cs(Accept-Language)":null,"x-rs-connection-negotiated-cipher-strength":"high","cs-categories":"Shopping;Software Downloads","s-supplier-failures":null,"cs-threat-risk":"unavailable","x-cs-ocsp-error":null,"cs-uri-scheme":"ssl","x-rs-certificate-hostname-threat-risk":"unavailable","cs-method":"unknown","cs-auth-group":null,"cs-ip":"192.168.1.1","x-virus-id":null,"c-ip":"192.168.1.1","s-ip":"192.168.1.1","rs(Content-Type)":null,"x-bluecoat-reference-id":"WA-LS-D_Standard-Deny2","x-rs-ocsp-error":null},{"x-cs-connection-negotiated-ssl-version":"TLSv1.2","x-cs-ocsp-error":null,"sc-status":0,"x-cs-connection-negotiated-cipher-strength":"high","x-rs-ocsp-error":null,"cs-uri-extension":null,"x-rs-certificate-observed-errors":"none","s-action":"TUNNELED","time":[18,31,59],"cs-username":null,"cs-method":"unknown","x-bluecoat-application-operation":"none","time-taken":421.0,"x-virus-id":null,"cs-host":"db5sch103091510.wns.windows.com","c-connect-type":"Transparent","cs-threat-risk":"unavailable","cs-ip":"192.168.1.1","x-rs-certificate-hostname-threat-risk":"unavailable","s-supplier-name":"db5sch103091510.wns.windows.com","cs-bytes":555,"x-rs-certificate-hostname":"*.wns.windows.com","x-rs-certificate-hostname-category":"Technology/Internet","sc-filter-result":"OBSERVED","cs(Accept-Language)":null,"x-bluecoat-reference-id":"WA-SP-A_Standard-Allow","s-supplier-country":"None","x-bluecoat-application-name":"none","x-exception-id":null,"cs-uri-port":443,"cs-auth-group":null,"x-rs-connection-negotiated-cipher-strength":"high","s-ip":"192.168.1.1","cs-categories":"Technology/Internet","sc-bytes":129,"rs(Content-Type)":null,"cs(Referer)":null,"s-supplier-ip":"192.168.1.1","date":[2018,2,2],"cs-uri-scheme":"ssl","s-supplier-failures":null,"c-ip":"192.168.1.1","cs(User-Agent)":null},{"time":[18,31,59],"cs-ip":"192.168.1.1","s-supplier-name":"www.google-analytics.com","rs(Content-Type)":null,"x-cs-connection-negotiated-ssl-version":"TLSv1.2","cs-uri-extension":null,"cs(Accept-Language)":null,"x-cs-ocsp-error":null,"cs(Referer)":null,"cs-auth-group":null,"x-cs-connection-negotiated-cipher-strength":"high","cs-categories":"Web Ads/Analytics","x-rs-certificate-hostname-threat-risk":"unavailable","sc-filter-result":"DENIED","cs-uri-port":443,"x-exception-id":"tenant.content_filter_denied","date":[2018,2,2],"x-bluecoat-application-operation":"none","x-bluecoat-application-name":"none","s-supplier-ip":"192.168.1.1","sc-bytes":0,"s-action":"DENIED","time-taken":1.0,"x-bluecoat-reference-id":"WA-LS-D_Standard-Deny2","x-rs-certificate-observed-errors":"none","cs(User-Agent)":null,"c-connect-type":"Transparent","cs-username":null,"s-ip":"192.168.1.1","c-ip":"192.168.1.1","x-rs-certificate-hostname":"*.google-analytics.com","cs-bytes":0,"s-supplier-country":"None","cs-method":"unknown","x-rs-certificate-hostname-category":"Web Ads/Analytics","x-rs-connection-negotiated-cipher-strength":"high","cs-uri-scheme":"ssl","s-supplier-failures":null,"sc-status":0,"x-virus-id":null,"x-rs-ocsp-error":null,"cs-threat-risk":"unavailable","cs-host":"www.google-analytics.com"},{"x-bluecoat-reference-id":"WA-LS-D_Standard-Deny2","s-supplier-failures":null,"s-supplier-ip":"192.168.1.1","cs-host":"play.google.com","x-rs-ocsp-error":null,"cs-ip":"192.168.1.1","s-supplier-country":"None","time":[18,31,59],"x-exception-id":"tenant.content_filter_denied","cs(Referer)":null,"x-cs-ocsp-error":null,"cs-auth-group":null,"s-ip":"192.168.1.1","x-bluecoat-application-operation":"none","x-rs-certificate-hostname-category":"Search Engines/Portals","rs(Content-Type)":null,"cs-uri-scheme":"ssl","cs-uri-port":443,"cs(User-Agent)":null,"date":[2018,2,2],"cs-threat-risk":"unavailable","c-connect-type":"Transparent","sc-status":0,"x-rs-certificate-hostname-threat-risk":"unavailable","cs-bytes":0,"s-supplier-name":"play.google.com","cs-method":"unknown","cs-uri-extension":null,"x-cs-connection-negotiated-ssl-version":"TLSv1.2","s-action":"DENIED","x-rs-connection-negotiated-cipher-strength":"high","sc-filter-result":"DENIED","x-cs-connection-negotiated-cipher-strength":"high","cs-username":null,"c-ip":"192.168.1.1","x-rs-certificate-hostname":"*.google.com","sc-bytes":0,"time-taken":1.0,"x-virus-id":null,"x-bluecoat-application-name":"none","cs(Accept-Language)":null,"x-rs-certificate-observed-errors":"none","cs-categories":"Shopping;Software Downloads"},{"cs-method":"unknown","cs-categories":"IA-Global-Permit;Technology/Internet","c-ip":"192.168.1.1","x-cs-connection-negotiated-cipher-strength":"high","c-connect-type":"Transparent","s-supplier-failures":null,"date":[2018,2,2],"s-supplier-name":"browser.pipe.aria.microsoft.com","x-virus-id":null,"x-rs-ocsp-error":null,"s-supplier-ip":"192.168.1.1","s-action":"TUNNELED","cs(User-Agent)":null,"x-exception-id":null,"x-rs-certificate-hostname-category":"Technology/Internet","cs-auth-group":null,"cs-uri-scheme":"ssl","cs(Referer)":null,"x-rs-certificate-hostname":"*.pipe.aria.microsoft.com","time":[18,31,59],"cs-host":"browser.pipe.aria.microsoft.com","sc-status":0,"time-taken":289.0,"x-bluecoat-reference-id":"WA-LS-A_Global-Exceptions","x-rs-connection-negotiated-cipher-strength":"high","x-bluecoat-application-operation":"none","cs-ip":"192.168.1.1","cs-uri-extension":null,"x-rs-certificate-observed-errors":"none","x-cs-ocsp-error":null,"cs-username":null,"cs-bytes":0,"cs-uri-port":443,"sc-bytes":0,"cs(Accept-Language)":null,"rs(Content-Type)":null,"x-rs-certificate-hostname-threat-risk":"unavailable","s-ip":"192.168.1.1","cs-threat-risk":"unavailable","sc-filter-result":"OBSERVED","s-supplier-country":"None","x-bluecoat-application-name":"none","x-cs-connection-negotiated-ssl-version":"TLSv1.2"},{"x-rs-connection-negotiated-cipher-strength":"high","sc-status":0,"s-action":"TUNNELED","date":[2018,2,2],"cs-username":null,"x-cs-connection-negotiated-cipher-strength":"high","time-taken":8488.0,"x-rs-certificate-hostname":"*.wns.windows.com","s-supplier-name":"db5sch103102311.wns.windows.com","x-virus-id":null,"cs-ip":"192.168.1.1","x-rs-certificate-observed-errors":"none","s-ip":"192.168.1.1","x-cs-connection-negotiated-ssl-version":"TLSv1.2","c-ip":"192.168.1.1","x-exception-id":null,"cs-categories":"Technology/Internet","x-bluecoat-application-operation":"none","cs-host":"db5sch103102311.wns.windows.com","cs-method":"unknown","sc-bytes":129,"x-bluecoat-reference-id":"WA-SP-A_Standard-Allow","x-rs-certificate-hostname-category":"Technology/Internet","s-supplier-failures":null,"s-supplier-ip":"192.168.1.1","cs-bytes":549,"sc-filter-result":"OBSERVED","x-rs-ocsp-error":null,"x-cs-ocsp-error":null,"cs-uri-port":443,"cs(Accept-Language)":null,"c-connect-type":"Transparent","x-rs-certificate-hostname-threat-risk":"unavailable","time":[18,31,59],"s-supplier-country":"None","cs-uri-scheme":"ssl","cs(Referer)":null,"cs(User-Agent)":null,"x-bluecoat-application-name":"none","cs-auth-group":null,"cs-uri-extension":null,"rs(Content-Type)":null,"cs-threat-risk":"unavailable"},{"c-ip":"192.168.1.1","cs-bytes":1668,"x-exception-id":null,"sc-filter-result":"OBSERVED","cs-auth-group":null,"x-virus-id":null,"cs-ip":"192.168.1.1","x-rs-certificate-hostname-threat-risk":"unavailable","sc-status":0,"date":[2018,2,2],"x-bluecoat-application-name":"none","s-supplier-failures":null,"x-cs-connection-negotiated-ssl-version":"TLSv1.2","x-rs-connection-negotiated-cipher-strength":"high","s-supplier-ip":"192.168.1.1","x-rs-certificate-hostname":"*.wns.windows.com","time":[18,31,59],"cs-uri-extension":null,"time-taken":376.0,"x-rs-certificate-hostname-category":"Technology/Internet","s-supplier-country":"None","x-bluecoat-reference-id":"WA-SP-A_Standard-Allow","cs-threat-risk":"unavailable","cs-username":null,"s-supplier-name":"client.wns.windows.com","cs-uri-port":443,"x-rs-certificate-observed-errors":"none","rs(Content-Type)":null,"x-rs-ocsp-error":null,"cs-categories":"Technology/Internet","s-action":"TUNNELED","s-ip":"192.168.1.1","x-cs-ocsp-error":null,"cs-method":"unknown","cs(Accept-Language)":null,"cs(User-Agent)":null,"sc-bytes":332,"cs-host":"client.wns.windows.com","cs-uri-scheme":"ssl","x-bluecoat-application-operation":"none","cs(Referer)":null,"x-cs-connection-negotiated-cipher-strength":"high","c-connect-type":"Transparent"},{"rs(Content-Type)":null,"cs-threat-risk":"unavailable","cs(Accept-Language)":null,"s-supplier-failures":null,"cs-uri-port":443,"time-taken":1.0,"s-action":"DENIED","x-rs-certificate-hostname":"*.eum-appdynamics.com","x-exception-id":"tenant.content_filter_denied","cs-ip":"192.168.1.1","c-ip":"192.168.1.1","cs-uri-scheme":"ssl","x-cs-connection-negotiated-ssl-version":"TLSv1","x-cs-ocsp-error":null,"x-bluecoat-application-operation":"none","sc-bytes":0,"sc-status":0,"x-rs-certificate-hostname-threat-risk":"unavailable","cs(User-Agent)":null,"s-supplier-ip":"192.168.1.1","cs-auth-group":null,"time":[18,31,59],"c-connect-type":"Transparent","cs-method":"unknown","sc-filter-result":"DENIED","x-rs-ocsp-error":null,"s-supplier-name":"col.eum-appdynamics.com","x-bluecoat-reference-id":"WA-LS-D_Standard-Deny2","cs-categories":"Web Ads/Analytics","x-virus-id":null,"cs-uri-extension":null,"x-cs-connection-negotiated-cipher-strength":"high","date":[2018,2,2],"x-bluecoat-application-name":"none","cs-bytes":0,"s-ip":"192.168.1.1","s-supplier-country":"None","x-rs-certificate-observed-errors":"none","cs-host":"col.eum-appdynamics.com","x-rs-connection-negotiated-cipher-strength":"high","x-rs-certificate-hostname-category":"Web Ads/Analytics","cs-username":null,"cs(Referer)":null},{"rs(Content-Type)":null,"s-supplier-country":"None","c-connect-type":"Transparent","cs-uri-port":443,"cs(User-Agent)":null,"cs-host":"client.wns.windows.com","cs-uri-scheme":"ssl","x-rs-certificate-hostname":"*.wns.windows.com","x-rs-certificate-hostname-threat-risk":"unavailable","x-rs-certificate-hostname-category":"Technology/Internet","x-rs-connection-negotiated-cipher-strength":"high","s-supplier-failures":null,"cs-threat-risk":"unavailable","cs-ip":"192.168.1.1","x-virus-id":null,"s-action":"TUNNELED","cs(Referer)":null,"s-supplier-ip":"192.168.1.1","sc-filter-result":"OBSERVED","x-rs-ocsp-error":null,"cs-auth-group":null,"s-ip":"192.168.1.1","time":[18,31,59],"cs-bytes":1706,"x-rs-certificate-observed-errors":"none","time-taken":238.0,"x-exception-id":null,"x-cs-connection-negotiated-ssl-version":"TLSv1.2","cs(Accept-Language)":null,"x-bluecoat-reference-id":"WA-SP-A_Standard-Allow","c-ip":"192.168.1.1","x-cs-connection-negotiated-cipher-strength":"high","x-bluecoat-application-name":"none","sc-status":0,"x-bluecoat-application-operation":"none","sc-bytes":332,"x-cs-ocsp-error":null,"cs-method":"unknown","s-supplier-name":"client.wns.windows.com","date":[2018,2,2],"cs-categories":"Technology/Internet","cs-uri-extension":null,"cs-username":null},{"cs-uri-extension":null,"cs(Accept-Language)":null,"s-action":"TUNNELED","c-connect-type":"Transparent","time":[18,31,59],"cs(User-Agent)":null,"cs-auth-group":null,"cs-uri-scheme":"ssl","rs(Content-Type)":null,"x-virus-id":null,"cs-ip":"192.168.1.1","sc-status":0,"cs-method":"unknown","time-taken":254.0,"x-rs-certificate-observed-errors":"none","s-supplier-ip":"192.168.1.1","sc-bytes":0,"s-ip":"192.168.1.1","x-rs-connection-negotiated-cipher-strength":"high","x-bluecoat-application-operation":"none","c-ip":"192.168.1.1","s-supplier-country":"None","x-rs-certificate-hostname":"*.pipe.aria.microsoft.com","x-exception-id":null,"cs-uri-port":443,"s-supplier-failures":null,"sc-filter-result":"OBSERVED","cs(Referer)":null,"x-bluecoat-application-name":"none","cs-threat-risk":"unavailable","s-supplier-name":"browser.pipe.aria.microsoft.com","x-bluecoat-reference-id":"WA-LS-A_Global-Exceptions","x-cs-connection-negotiated-cipher-strength":"high","x-rs-certificate-hostname-category":"Technology/Internet","cs-bytes":0,"x-rs-certificate-hostname-threat-risk":"unavailable","cs-host":"browser.pipe.aria.microsoft.com","x-rs-ocsp-error":null,"x-cs-connection-negotiated-ssl-version":"TLSv1.2","cs-username":null,"x-cs-ocsp-error":null,"cs-categories":"IA-Global-Permit;Technology/Internet","date":[2018,2,2]},{"cs-uri-extension":null,"c-ip":"192.168.1.1","s-action":"TUNNELED","cs-auth-group":null,"x-virus-id":null,"s-supplier-ip":"192.168.1.1","cs-method":"unknown","x-rs-certificate-hostname-threat-risk":"unavailable","cs-uri-port":443,"cs-uri-scheme":"ssl","s-supplier-failures":null,"time":[18,31,59],"x-rs-certificate-hostname-category":"Technology/Internet","cs(Accept-Language)":null,"s-supplier-name":"db5sch103090914.wns.windows.com","x-cs-ocsp-error":null,"x-bluecoat-application-operation":"none","sc-status":0,"date":[2018,2,2],"x-rs-ocsp-error":null,"c-connect-type":"Transparent","x-rs-certificate-hostname":"*.wns.windows.com","x-rs-certificate-observed-errors":"none","x-cs-connection-negotiated-ssl-version":"TLSv1.2","x-exception-id":null,"sc-bytes":129,"s-ip":"192.168.1.1","x-bluecoat-application-name":"none","cs-username":null,"sc-filter-result":"OBSERVED","cs(User-Agent)":null,"s-supplier-country":"None","cs-threat-risk":"unavailable","cs(Referer)":null,"cs-categories":"Technology/Internet","cs-bytes":524,"x-rs-connection-negotiated-cipher-strength":"high","time-taken":15460.0,"cs-ip":"192.168.1.1","cs-host":"db5sch103090914.wns.windows.com","rs(Content-Type)":null,"x-bluecoat-reference-id":"WA-SP-A_Standard-Allow","x-cs-connection-negotiated-cipher-strength":"high"},{"cs-threat-risk":"unavailable","cs-uri-port":443,"x-exception-id":null,"sc-bytes":129,"s-supplier-ip":"192.168.1.1","date":[2018,2,2],"cs-auth-group":null,"cs(Referer)":null,"x-bluecoat-application-name":"none","cs-bytes":550,"x-rs-connection-negotiated-cipher-strength":"high","s-supplier-country":"None","c-connect-type":"Transparent","s-supplier-name":"db6sch102091603.wns.windows.com","c-ip":"192.168.1.1","rs(Content-Type)":null,"x-cs-connection-negotiated-ssl-version":"TLSv1.2","cs-username":null,"cs(User-Agent)":null,"x-bluecoat-application-operation":"none","s-supplier-failures":null,"cs-host":"db6sch102091603.wns.windows.com","time":[18,31,59],"x-rs-certificate-observed-errors":"none","cs-categories":"Technology/Internet","x-bluecoat-reference-id":"WA-SP-A_Standard-Allow","x-rs-certificate-hostname-category":"Technology/Internet","s-ip":"192.168.1.1","sc-status":0,"sc-filter-result":"OBSERVED","x-rs-certificate-hostname-threat-risk":"unavailable","cs-method":"unknown","x-cs-ocsp-error":null,"time-taken":6360.0,"cs-uri-scheme":"ssl","cs(Accept-Language)":null,"s-action":"TUNNELED","x-rs-ocsp-error":null,"x-virus-id":null,"x-rs-certificate-hostname":"*.wns.windows.com","cs-ip":"192.168.1.1","x-cs-connection-negotiated-cipher-strength":"high","cs-uri-extension":null},{"cs-categories":"none","cs-ip":"192.168.1.1","sc-filter-result":"DENIED","x-rs-certificate-hostname":"*.cloudconnect.envisionware.net","rs(Content-Type)":null,"cs(Accept-Language)":null,"sc-bytes":0,"cs-username":null,"x-virus-id":null,"s-action":"DENIED","s-supplier-ip":"192.168.1.1","cs(Referer)":null,"cs-bytes":0,"x-bluecoat-application-operation":"none","cs-host":"api.cloudconnect.envisionware.net","x-cs-connection-negotiated-ssl-version":"TLSv1.2","x-cs-ocsp-error":null,"sc-status":0,"x-rs-ocsp-error":null,"c-connect-type":"Transparent","x-cs-connection-negotiated-cipher-strength":"high","c-ip":"192.168.1.1","s-ip":"192.168.1.1","cs(User-Agent)":null,"x-exception-id":"tenant.content_filter_denied","cs-auth-group":null,"x-rs-certificate-observed-errors":"none","s-supplier-country":"None","date":[2018,2,2],"time":[18,31,59],"time-taken":1.0,"s-supplier-name":"api.cloudconnect.envisionware.net","cs-threat-risk":"unavailable","x-rs-certificate-hostname-category":"none","cs-uri-scheme":"ssl","cs-uri-port":443,"s-supplier-failures":null,"x-bluecoat-reference-id":"WA-SP-D_Cat-None","x-rs-certificate-hostname-threat-risk":"unavailable","x-bluecoat-application-name":"none","x-rs-connection-negotiated-cipher-strength":"high","cs-method":"unknown","cs-uri-extension":null},{"x-bluecoat-reference-id":"WA-SP-A_Standard-Allow","x-rs-certificate-hostname-threat-risk":"unavailable","cs-uri-port":443,"cs-auth-group":null,"x-rs-ocsp-error":null,"s-supplier-name":"fonts.gstatic.com","cs-ip":"192.168.1.1","c-connect-type":"Transparent","x-exception-id":null,"x-rs-certificate-hostname":"*.google.com","c-ip":"192.168.1.1","time-taken":10713.0,"cs(User-Agent)":null,"time":[18,31,59],"date":[2018,2,2],"cs-uri-extension":null,"sc-bytes":4327,"x-rs-certificate-observed-errors":"none","x-bluecoat-application-operation":"none","x-cs-ocsp-error":null,"rs(Content-Type)":null,"s-action":"TUNNELED","x-rs-certificate-hostname-category":"Search Engines/Portals","s-ip":"192.168.1.1","cs-method":"unknown","x-cs-connection-negotiated-ssl-version":"TLSv1.2","s-supplier-country":"None","cs-threat-risk":"unavailable","cs(Referer)":null,"sc-filter-result":"OBSERVED","cs(Accept-Language)":null,"sc-status":0,"cs-categories":"Search Engines/Portals","x-rs-connection-negotiated-cipher-strength":"high","x-virus-id":null,"cs-uri-scheme":"ssl","cs-host":"fonts.gstatic.com","x-bluecoat-application-name":"none","cs-bytes":93,"cs-username":null,"s-supplier-failures":null,"s-supplier-ip":"192.168.1.1","x-cs-connection-negotiated-cipher-strength":"high"},{"x-rs-certificate-hostname-threat-risk":"unavailable","s-action":"DENIED","cs-uri-port":443,"cs-categories":"Web Ads/Analytics","cs-auth-group":null,"x-exception-id":"tenant.content_filter_denied","c-connect-type":"Transparent","time":[18,31,59],"s-supplier-name":"datacloud.tealiumiq.com","s-supplier-ip":"192.168.1.1","cs(Accept-Language)":null,"cs-username":null,"x-virus-id":null,"sc-filter-result":"DENIED","x-rs-certificate-hostname":"*.tealiumiq.com","sc-bytes":0,"x-rs-ocsp-error":null,"cs-ip":"192.168.1.1","time-taken":1.0,"cs-method":"unknown","s-supplier-country":"None","s-supplier-failures":null,"cs(User-Agent)":null,"x-rs-connection-negotiated-cipher-strength":"high","cs(Referer)":null,"s-ip":"192.168.1.1","x-bluecoat-reference-id":"WA-LS-D_Standard-Deny2","rs(Content-Type)":null,"x-cs-connection-negotiated-cipher-strength":"high","cs-threat-risk":"unavailable","x-rs-certificate-hostname-category":"Business/Economy","x-bluecoat-application-name":"none","sc-status":0,"cs-host":"datacloud.tealiumiq.com","cs-uri-scheme":"ssl","x-cs-ocsp-error":null,"date":[2018,2,2],"c-ip":"192.168.1.1","x-cs-connection-negotiated-ssl-version":"TLSv1.2","x-rs-certificate-observed-errors":"none","x-bluecoat-application-operation":"none","cs-uri-extension":null,"cs-bytes":0},{"x-exception-id":"tenant.content_filter_denied","x-bluecoat-application-operation":"none","cs-host":"datacloud.tealiumiq.com","c-ip":"192.168.1.1","cs(Referer)":null,"cs-username":null,"x-cs-ocsp-error":null,"time-taken":1.0,"cs-ip":"192.168.1.1","x-rs-certificate-observed-errors":"none","s-supplier-ip":"192.168.1.1","s-supplier-name":"datacloud.tealiumiq.com","x-bluecoat-reference-id":"WA-LS-D_Standard-Deny2","s-action":"DENIED","x-rs-connection-negotiated-cipher-strength":"high","cs(Accept-Language)":null,"rs(Content-Type)":null,"cs-threat-risk":"unavailable","sc-filter-result":"DENIED","cs-auth-group":null,"x-cs-connection-negotiated-ssl-version":"TLSv1.2","cs-uri-port":443,"s-supplier-country":"None","time":[18,31,59],"x-rs-certificate-hostname-threat-risk":"unavailable","x-rs-certificate-hostname":"*.tealiumiq.com","x-cs-connection-negotiated-cipher-strength":"high","s-supplier-failures":null,"sc-status":0,"x-virus-id":null,"x-bluecoat-application-name":"none","cs-method":"unknown","x-rs-certificate-hostname-category":"Business/Economy","sc-bytes":0,"cs-uri-scheme":"ssl","cs-uri-extension":null,"cs-categories":"Web Ads/Analytics","c-connect-type":"Transparent","date":[2018,2,2],"x-rs-ocsp-error":null,"cs-bytes":0,"cs(User-Agent)":null,"s-ip":"192.168.1.1"},{"x-cs-connection-negotiated-ssl-version":"TLSv1.2","s-ip":"192.168.1.1","x-cs-ocsp-error":null,"x-exception-id":"tenant.content_filter_denied","cs(User-Agent)":null,"sc-bytes":0,"sc-status":0,"x-virus-id":null,"x-rs-ocsp-error":null,"s-supplier-country":"None","cs-auth-group":null,"x-bluecoat-reference-id":"WA-LS-D_Standard-Deny2","cs-categories":"Shopping;Software Downloads","s-action":"DENIED","x-rs-certificate-observed-errors":"none","time":[18,31,59],"x-cs-connection-negotiated-cipher-strength":"high","cs-uri-port":443,"x-rs-certificate-hostname-threat-risk":"unavailable","cs-uri-scheme":"ssl","c-ip":"192.168.1.1","s-supplier-failures":null,"cs(Accept-Language)":null,"cs-threat-risk":"unavailable","cs-username":null,"cs(Referer)":null,"x-bluecoat-application-operation":"none","cs-bytes":0,"time-taken":1.0,"cs-host":"play.google.com","x-rs-certificate-hostname":"*.google.com","cs-uri-extension":null,"x-bluecoat-application-name":"none","x-rs-certificate-hostname-category":"Search Engines/Portals","rs(Content-Type)":null,"x-rs-connection-negotiated-cipher-strength":"high","date":[2018,2,2],"cs-method":"unknown","c-connect-type":"Transparent","s-supplier-name":"play.google.com","s-supplier-ip":"192.168.1.1","cs-ip":"192.168.1.1","sc-filter-result":"DENIED"},{"s-action":"TUNNELED","c-connect-type":"Transparent","cs-categories":"Technology/Internet","cs-username":null,"x-exception-id":null,"sc-bytes":129,"s-supplier-country":"None","cs(Accept-Language)":null,"time-taken":17587.0,"c-ip":"192.168.1.1","x-cs-connection-negotiated-ssl-version":"TLSv1.2","x-rs-certificate-hostname-threat-risk":"unavailable","cs-ip":"192.168.1.1","cs(Referer)":null,"cs-threat-risk":"unavailable","x-rs-certificate-hostname-category":"Technology/Internet","cs-host":"db6sch102090309.wns.windows.com","x-rs-certificate-hostname":"*.wns.windows.com","x-rs-ocsp-error":null,"time":[18,31,59],"cs-method":"unknown","x-bluecoat-application-operation":"none","s-supplier-name":"db6sch102090309.wns.windows.com","rs(Content-Type)":null,"x-rs-certificate-observed-errors":"none","s-supplier-ip":"192.168.1.1","cs-bytes":554,"x-cs-connection-negotiated-cipher-strength":"high","cs-auth-group":null,"date":[2018,2,2],"cs-uri-extension":null,"sc-filter-result":"OBSERVED","cs-uri-scheme":"ssl","s-ip":"192.168.1.1","x-rs-connection-negotiated-cipher-strength":"high","x-cs-ocsp-error":null,"sc-status":0,"cs-uri-port":443,"x-virus-id":null,"x-bluecoat-application-name":"none","x-bluecoat-reference-id":"WA-SP-A_Standard-Allow","cs(User-Agent)":null,"s-supplier-failures":null},{"x-virus-id":null,"cs-auth-group":null,"date":[2018,2,2],"rs(Content-Type)":null,"x-exception-id":null,"cs(Accept-Language)":null,"sc-filter-result":"OBSERVED","x-rs-ocsp-error":null,"c-ip":"192.168.1.1","x-rs-certificate-hostname-category":"Technology/Internet","s-ip":"192.168.1.1","time-taken":14679.0,"cs-username":null,"cs-host":"db5sch101102033.wns.windows.com","cs-threat-risk":"unavailable","x-bluecoat-application-operation":"none","cs(User-Agent)":null,"s-supplier-ip":"192.168.1.1","s-action":"TUNNELED","x-rs-connection-negotiated-cipher-strength":"high","sc-bytes":129,"cs(Referer)":null,"sc-status":0,"x-rs-certificate-hostname":"*.wns.windows.com","cs-uri-extension":null,"s-supplier-country":"None","s-supplier-failures":null,"cs-uri-port":443,"cs-method":"unknown","x-cs-connection-negotiated-ssl-version":"TLSv1.2","x-cs-connection-negotiated-cipher-strength":"high","s-supplier-name":"db5sch101102033.wns.windows.com","cs-ip":"192.168.1.1","x-rs-certificate-observed-errors":"none","x-bluecoat-reference-id":"WA-SP-A_Standard-Allow","x-rs-certificate-hostname-threat-risk":"unavailable","cs-categories":"Technology/Internet","time":[18,31,59],"x-cs-ocsp-error":null,"cs-uri-scheme":"ssl","x-bluecoat-application-name":"none","c-connect-type":"Transparent","cs-bytes":550},{"cs-host":"play.google.com","x-bluecoat-application-name":"none","cs-uri-port":443,"s-ip":"192.168.1.1","time-taken":1.0,"cs(Referer)":null,"s-supplier-name":"play.google.com","rs(Content-Type)":null,"cs-threat-risk":"unavailable","s-supplier-ip":"192.168.1.1","s-supplier-country":"None","date":[2018,2,2],"cs(User-Agent)":null,"c-connect-type":"Transparent","cs-uri-scheme":"ssl","x-virus-id":null,"cs(Accept-Language)":null,"sc-status":0,"x-cs-connection-negotiated-cipher-strength":"high","time":[18,31,59],"x-rs-connection-negotiated-cipher-strength":"high","s-supplier-failures":null,"x-cs-connection-negotiated-ssl-version":"TLSv1.2","cs-auth-group":null,"x-rs-certificate-hostname-category":"Search Engines/Portals","x-rs-certificate-hostname-threat-risk":"unavailable","c-ip":"192.168.1.1","cs-username":null,"sc-bytes":0,"sc-filter-result":"DENIED","x-cs-ocsp-error":null,"x-rs-ocsp-error":null,"x-exception-id":"tenant.content_filter_denied","cs-method":"unknown","cs-uri-extension":null,"x-bluecoat-application-operation":"none","x-rs-certificate-hostname":"*.google.com","x-rs-certificate-observed-errors":"none","cs-bytes":0,"cs-categories":"Shopping;Software Downloads","cs-ip":"192.168.1.1","x-bluecoat-reference-id":"WA-LS-D_Standard-Deny2","s-action":"DENIED"}]}