{"input":"#Software: xyz 1.2.3.4\n#Version: 1.0\n#Start-Date: 2019-10-23 22:00:00\n#Date: 2019-10-23 22:00:00\n#Fields: date time time-taken ip1 user gp id1 res cat1 status act method ct scheme host port ext ua ip2 bytes1 bytes2 id2 err1 err2 err3 str cr cat2\n#Remark: 1234567890 \"xyz\" \"1.2.3.4\" \"type\"\n2019-10-23    21:00:00    1234    1.2.3.4    xyz    abc    -    OK    \"cat\"    0    zyx    unk    -    pro    site    123    -    -    1.2.3.4    0    0    -    none    -    -    none    -    \"cat\"\n2019-10-23    21:00:00    123    1.2.3.4    xyz    abc    -    OK    \"dog\"    0    zyx    unk    -    pro    site    123    -    -    1.2.3.4    0    0    -    none    -    -    none    -    \"dog\"","expected":[{"bytes2":0,"str":"none","ua":null,"ext":null,"bytes1":0,"host":"site","scheme":"pro","time":[21,0],"err3":null,"status":"0","user":"xyz","ct":null,"cat2":"cat","id1":null,"err2":null,"ip2":"1.2.3.4","method":"unk","time-taken":1234.0,"res":"OK","id2":null,"date":[2019,10,23],"err1":"none","act":"zyx","ip1":"1.2.3.4","port":"123","cat1":"cat","cr":null,"gp":"abc"},{"ext":null,"time":[21,0],"ua":null,"err3":null,"res":"OK","method":"unk","status":"0","port":"123","bytes2":0,"gp":"abc","id1":null,"cr":null,"str":"none","act":"zyx","time-taken":123.0,"err2":null,"cat2":"dog","err1":"none","scheme":"pro","ct":null,"date":[2019,10,23],"cat1":"dog","ip1":"1.2.3.4","ip2":"1.2.3.4","host":"site","user":"xyz","bytes1":0,"id2":null}]}